05_arbiters/fixed_priority_arbiter.sv
// =============================================================================
// fixed_priority_arbiter.sv - Fixed-Priority Arbiter
// -----------------------------------------------------------------------------
// N requesters compete for one shared resource. Requester 0 always wins if it
// asks; requester 1 wins only if 0 doesn't ask; and so on down the line. This
// is the simplest possible arbiter -- purely combinational, one-hot grant.
//
// Pros: trivial to implement, zero latency, deterministic.
// Cons: low-priority requesters can be starved forever if a high-priority
//       requester keeps asking. (This is exactly why round_robin_arbiter.sv
//       exists -- see that file for the fairness fix.)
// =============================================================================
module fixed_priority_arbiter #(
    parameter int N = 4                        // number of requesters
) (
    input  logic [N-1:0] req,                  // req[0] = highest priority
    output logic [N-1:0] grant                 // one-hot (or all-zero if no request)
);

    // grant[i] = req[i] AND none of the higher-priority requesters (0..i-1) are asking
    always_comb begin
        grant = '0;
        for (int i = 0; i < N; i++) begin
            if (req[i] && !(|(req & ((1 << i) - 1)))) begin
                grant[i] = 1'b1;
            end
        end
    end

endmodule

05_arbiters/tb_fixed_priority_arbiter.sv
// =============================================================================
// tb_fixed_priority_arbiter.sv
// =============================================================================
`timescale 1ns/1ps
module tb_fixed_priority_arbiter;

    localparam int N = 4;
    logic [N-1:0] req;
    logic [N-1:0] grant;
    int errors = 0, checks = 0;

    fixed_priority_arbiter #(.N(N)) dut (.req(req), .grant(grant));

    initial begin
        $dumpfile("fixed_priority_arbiter.vcd");
        $dumpvars(0, tb_fixed_priority_arbiter);
    end

    function automatic [N-1:0] expected_grant(input [N-1:0] r);
        expected_grant = '0;
        for (int i = 0; i < N; i++) begin
            if (r[i]) begin
                expected_grant = (1 << i);
                return expected_grant;
            end
        end
    endfunction

    task automatic check(input [N-1:0] r);
        logic [N-1:0] exp;
        req = r;
        #1;
        exp = expected_grant(r);
        checks++;
        if (grant !== exp) begin
            $display("ERROR: req=%b grant=%b expected=%b", r, grant, exp);
            errors++;
        end
    endtask

    initial begin
        // Exhaustively test all 2^N request combinations -- fully feasible since N is small
        for (int r = 0; r < (1<<N); r++) begin
            check(r[N-1:0]);
        end

        $display("--------------------------------------------------");
        if (errors == 0) $display("FIXED_PRIORITY_ARBITER: ALL %0d CHECKS PASSED (exhaustive, N=%0d)", checks, N);
        else $display("FIXED_PRIORITY_ARBITER: %0d ERRORS out of %0d checks", errors, checks);
        $display("--------------------------------------------------");
        #20 $finish;
    end
endmodule

05_arbiters/fixed_priority_arbiter.vcd
$date
	Wed Jul  1 19:58:01 2026
$end
$version
	Icarus Verilog
$end
$timescale
	1ps
$end
$scope module tb_fixed_priority_arbiter $end
$var wire 4 ! grant [3:0] $end
$var parameter 32 " N $end
$var reg 4 # req [3:0] $end
$var integer 32 $ checks [31:0] $end
$var integer 32 % errors [31:0] $end
$scope function expected_grant $end
$scope begin $ivl_for_loop1 $end
$upscope $end
$upscope $end
$scope module dut $end
$var wire 4 & req [3:0] $end
$var parameter 32 ' N $end
$var reg 4 ( grant [3:0] $end
$scope begin $ivl_for_loop0 $end
$var integer 32 ) i [31:0] $end
$upscope $end
$upscope $end
$scope begin $ivl_for_loop2 $end
$var integer 32 * r [31:0] $end
$upscope $end
$scope task check $end
$upscope $end
$upscope $end
$enddefinitions $end
$comment Show the parameter values. $end
$dumpall
b100 '
b100 "
$end
#0
$dumpvars
b0 *
b100 )
b0 (
b0 &
b0 %
b0 $
b0 #
b0 !
$end
#1000
b1 !
b1 (
b100 )
b1 #
b1 &
b1 *
b1 $
#2000
b100 )
b10 !
b10 (
b10 #
b10 &
b10 *
b10 $
#3000
b100 )
b1 !
b1 (
b11 #
b11 &
b11 *
b11 $
#4000
b100 )
b100 !
b100 (
b100 #
b100 &
b100 *
b100 $
#5000
b100 )
b1 !
b1 (
b101 #
b101 &
b101 *
b101 $
#6000
b100 )
b10 !
b10 (
b110 #
b110 &
b110 *
b110 $
#7000
b100 )
b1 !
b1 (
b111 #
b111 &
b111 *
b111 $
#8000
b100 )
b1000 !
b1000 (
b1000 #
b1000 &
b1000 *
b1000 $
#9000
b100 )
b1 !
b1 (
b1001 #
b1001 &
b1001 *
b1001 $
#10000
b100 )
b10 !
b10 (
b1010 #
b1010 &
b1010 *
b1010 $
#11000
b100 )
b1 !
b1 (
b1011 #
b1011 &
b1011 *
b1011 $
#12000
b100 )
b100 !
b100 (
b1100 #
b1100 &
b1100 *
b1100 $
#13000
b100 )
b1 !
b1 (
b1101 #
b1101 &
b1101 *
b1101 $
#14000
b100 )
b10 !
b10 (
b1110 #
b1110 &
b1110 *
b1110 $
#15000
b100 )
b1 !
b1 (
b1111 #
b1111 &
b1111 *
b1111 $
#16000
b10000 *
b10000 $
