05_arbiters/round_robin_arbiter.sv
// =============================================================================
// round_robin_arbiter.sv - Round-Robin Arbiter
// -----------------------------------------------------------------------------
// Fixes the starvation problem of a fixed-priority arbiter: after granting
// requester K, the priority pointer moves to K+1, so K becomes the LOWEST
// priority requester for the next arbitration. Every requester eventually
// gets a turn as long as it keeps asking -- no one can be starved forever by
// a higher-priority neighbor.
//
// Implementation trick: rather than writing separate "wrap-around priority"
// logic, we DOUBLE the request vector (concatenate req with itself) and scan
// a WINDOW of N consecutive bits starting at the pointer's position. The
// first requester found scanning left-to-right through that window wins.
// Because the vector is doubled, the window can "wrap past bit N-1 back to
// bit 0" for free, without any special-case wrap-around code.
// =============================================================================
module round_robin_arbiter #(
    parameter int N = 4
) (
    input  logic          clk,
    input  logic          rst_n,
    input  logic [N-1:0]  req,
    output logic [N-1:0]  grant                // one-hot (or all-zero if no request)
);

    localparam int PW = (N <= 1) ? 1 : $clog2(N);

    logic [PW-1:0] ptr;             // "highest priority this round" pointer (0..N-1)
    logic [2*N-1:0] req_double;     // req concatenated with itself
    logic [2*N-1:0] grant_double;
    logic [PW-1:0] winner_pos;
    logic          any_grant;

    assign req_double = {req, req};

    // Scan the window [ptr, ptr+N) left to right; the FIRST requester found
    // asking wins. 'found' stops us granting more than one bit.
    always @(*) begin
        grant_double = '0;
        winner_pos   = ptr;
        any_grant    = 1'b0;
        for (int i = 0; i < 2*N; i++) begin
            if (!any_grant && i >= ptr && i < ptr + N && req_double[i]) begin
                grant_double[i] = 1'b1;
                winner_pos      = i % N;
                any_grant       = 1'b1;
            end
        end
    end

    // Fold the doubled grant vector back down to N bits (bit i and bit i+N
    // represent the same physical requester; only one of the two is ever set)
    assign grant = grant_double[N-1:0] | grant_double[2*N-1:N];

    // Advance the pointer to (winner + 1) so the winner becomes lowest
    // priority next time. If nobody won (no requests), pointer holds.
    always_ff @(posedge clk or negedge rst_n) begin
        if (!rst_n)          ptr <= '0;
        else if (any_grant)  ptr <= (winner_pos + 1'b1) % N;
    end

endmodule

05_arbiters/tb_round_robin_arbiter.sv
// =============================================================================
// tb_round_robin_arbiter.sv
// =============================================================================
`timescale 1ns/1ps
module tb_round_robin_arbiter;

    localparam int N = 4;
    logic clk = 0, rst_n;
    logic [N-1:0] req;
    logic [N-1:0] grant;
    int errors = 0, checks = 0;
    int grant_count [N];

    round_robin_arbiter #(.N(N)) dut (.clk(clk), .rst_n(rst_n), .req(req), .grant(grant));

    always #5 clk = ~clk;

    initial begin
        $dumpfile("round_robin_arbiter.vcd");
        $dumpvars(0, tb_round_robin_arbiter);
    end

    // Basic legality checks every cycle: grant must be one-hot AND a subset of req
    always @(posedge clk) begin
        if (rst_n) begin
            checks++;
            if (grant != 0 && $countones(grant) != 1) begin
                $display("[%0t] ERROR: grant=%b is not one-hot", $time, grant);
                errors++;
            end
            if ((grant & ~req) != 0) begin
                $display("[%0t] ERROR: grant=%b includes a bit not in req=%b", $time, grant, req);
                errors++;
            end
            for (int i = 0; i < N; i++) if (grant[i]) grant_count[i]++;
        end
    end

    initial begin
        req = '0;
        rst_n = 0;
        for (int i = 0; i < N; i++) grant_count[i] = 0;
        repeat (3) @(posedge clk);
        rst_n = 1;
        @(negedge clk);

        // --- Test 1: all 4 requesters constantly asking -> should cycle fairly ---
        req = 4'b1111;
        repeat (40) @(posedge clk);
        @(negedge clk);   // let the grant_count-updating always block settle before we read it

        $display("After 40 cycles, all requesting: grant_count = [%0d, %0d, %0d, %0d]",
                  grant_count[0], grant_count[1], grant_count[2], grant_count[3]);
        checks++;
        for (int i = 0; i < N; i++) begin
            if (grant_count[i] < 8) begin   // expect ~10 each; allow slack, but nobody starved
                $display("ERROR: requester %0d only got %0d grants out of 40 (possible starvation)", i, grant_count[i]);
                errors++;
            end
        end

        // --- Test 2: only requester 3 asks -> it should get every grant, no starving itself ---
        @(negedge clk); req = 4'b1000;
        repeat (10) @(posedge clk);
        @(negedge clk);   // let the grant_count-updating always block settle before we read it
        checks++;
        if (grant_count[3] < 8) begin  // it was already accumulating from test1 too; just sanity check it keeps winning
            $display("NOTE: requester 3 solo count=%0d", grant_count[3]);
        end

        // --- Test 3: requester 0 asks continuously, others silent -> req0 should win every time ---
        for (int i = 0; i < N; i++) grant_count[i] = 0;
        @(negedge clk); req = 4'b0001;
        repeat (10) @(posedge clk);
        @(negedge clk);   // let the grant_count-updating always block settle before we read it
        checks++;
        if (grant_count[0] != 10) begin
            $display("ERROR: sole requester 0 expected 10/10 grants, got %0d", grant_count[0]);
            errors++;
        end

        // --- Test 4: alternating pair (0 and 2) both constantly requesting ---
        for (int i = 0; i < N; i++) grant_count[i] = 0;
        @(negedge clk); req = 4'b0101;
        repeat (20) @(posedge clk);
        @(negedge clk);   // let the grant_count-updating always block settle before we read it
        checks++;
        if (grant_count[0] < 8 || grant_count[2] < 8) begin
            $display("ERROR: unfair split between requesters 0 and 2: %0d vs %0d", grant_count[0], grant_count[2]);
            errors++;
        end else begin
            $display("Fair split between 0 and 2: %0d vs %0d (out of 20)", grant_count[0], grant_count[2]);
        end

        req = '0;
        repeat (3) @(posedge clk);

        $display("--------------------------------------------------");
        if (errors == 0) $display("ROUND_ROBIN_ARBITER: ALL %0d CHECKS PASSED", checks);
        else $display("ROUND_ROBIN_ARBITER: %0d ERRORS out of %0d checks", errors, checks);
        $display("--------------------------------------------------");
        #20 $finish;
    end
endmodule

05_arbiters/round_robin_arbiter.vcd
$date
	Wed Jul  1 19:57:46 2026
$end
$version
	Icarus Verilog
$end
$timescale
	1ps
$end
$scope module tb_round_robin_arbiter $end
$var wire 4 ! grant [3:0] $end
$var parameter 32 " N $end
$var reg 1 # clk $end
$var reg 4 $ req [3:0] $end
$var reg 1 % rst_n $end
$var integer 32 & checks [31:0] $end
$var integer 32 ' errors [31:0] $end
$scope module dut $end
$var wire 1 # clk $end
$var wire 4 ( grant [3:0] $end
$var wire 4 ) req [3:0] $end
$var wire 1 % rst_n $end
$var wire 8 * req_double [7:0] $end
$var parameter 32 + N $end
$var parameter 32 , PW $end
$var reg 1 - any_grant $end
$var reg 8 . grant_double [7:0] $end
$var reg 2 / ptr [1:0] $end
$var reg 2 0 winner_pos [1:0] $end
$scope begin $ivl_for_loop0 $end
$var integer 32 1 i [31:0] $end
$upscope $end
$upscope $end
$scope begin $ivl_for_loop1 $end
$var integer 32 2 i [31:0] $end
$upscope $end
$scope begin $ivl_for_loop2 $end
$var integer 32 3 i [31:0] $end
$upscope $end
$scope begin $ivl_for_loop3 $end
$var integer 32 4 i [31:0] $end
$upscope $end
$scope begin $ivl_for_loop4 $end
$var integer 32 5 i [31:0] $end
$upscope $end
$scope begin $ivl_for_loop5 $end
$var integer 32 6 i [31:0] $end
$upscope $end
$upscope $end
$enddefinitions $end
$comment Show the parameter values. $end
$dumpall
b10 ,
b100 +
b100 "
$end
#0
$dumpvars
b0 6
b0 5
b0 4
b100 3
b0 2
b1000 1
b0 0
b0 /
b0 .
0-
b0 *
b0 )
b0 (
b0 '
b0 &
0%
b0 $
0#
b0 !
$end
#5000
1#
#10000
0#
#15000
1#
#20000
0#
#25000
b100 2
b1 &
1%
1#
#30000
b1 !
b1 (
1-
b1 .
b1000 1
b11111111 *
b1111 $
b1111 )
0#
#35000
b10 !
b10 (
b1000 1
1-
b1 0
b10 .
b1 /
b100 2
b10 &
1#
#40000
0#
#45000
b100 !
b100 (
b1000 1
1-
b10 0
b100 .
b10 /
b100 2
b11 &
1#
#50000
0#
#55000
b1000 !
b1000 (
b1000 1
1-
b11 0
b1000 .
b11 /
b100 2
b100 &
1#
#60000
0#
#65000
b1 !
b1 (
b1000 1
1-
b0 0
b1 .
b0 /
b100 2
b101 &
1#
#70000
0#
#75000
b10 !
b10 (
b1000 1
1-
b1 0
b10 .
b1 /
b100 2
b110 &
1#
#80000
0#
#85000
b100 !
b100 (
b1000 1
1-
b10 0
b100 .
b10 /
b100 2
b111 &
1#
#90000
0#
#95000
b1000 !
b1000 (
b1000 1
1-
b11 0
b1000 .
b11 /
b100 2
b1000 &
1#
#100000
0#
#105000
b1 !
b1 (
b1000 1
1-
b0 0
b1 .
b0 /
b100 2
b1001 &
1#
#110000
0#
#115000
b10 !
b10 (
b1000 1
1-
b1 0
b10 .
b1 /
b100 2
b1010 &
1#
#120000
0#
#125000
b100 !
b100 (
b1000 1
1-
b10 0
b100 .
b10 /
b100 2
b1011 &
1#
#130000
0#
#135000
b1000 !
b1000 (
b1000 1
1-
b11 0
b1000 .
b11 /
b100 2
b1100 &
1#
#140000
0#
#145000
b1 !
b1 (
b1000 1
1-
b0 0
b1 .
b0 /
b100 2
b1101 &
1#
#150000
0#
#155000
b10 !
b10 (
b1000 1
1-
b1 0
b10 .
b1 /
b100 2
b1110 &
1#
#160000
0#
#165000
b100 !
b100 (
b1000 1
1-
b10 0
b100 .
b10 /
b100 2
b1111 &
1#
#170000
0#
#175000
b1000 !
b1000 (
b1000 1
1-
b11 0
b1000 .
b11 /
b100 2
b10000 &
1#
#180000
0#
#185000
b1 !
b1 (
b1000 1
1-
b0 0
b1 .
b0 /
b100 2
b10001 &
1#
#190000
0#
#195000
b10 !
b10 (
b1000 1
1-
b1 0
b10 .
b1 /
b100 2
b10010 &
1#
#200000
0#
#205000
b100 !
b100 (
b1000 1
1-
b10 0
b100 .
b10 /
b100 2
b10011 &
1#
#210000
0#
#215000
b1000 !
b1000 (
b1000 1
1-
b11 0
b1000 .
b11 /
b100 2
b10100 &
1#
#220000
0#
#225000
b1 !
b1 (
b1000 1
1-
b0 0
b1 .
b0 /
b100 2
b10101 &
1#
#230000
0#
#235000
b10 !
b10 (
b1000 1
1-
b1 0
b10 .
b1 /
b100 2
b10110 &
1#
#240000
0#
#245000
b100 !
b100 (
b1000 1
1-
b10 0
b100 .
b10 /
b100 2
b10111 &
1#
#250000
0#
#255000
b1000 !
b1000 (
b1000 1
1-
b11 0
b1000 .
b11 /
b100 2
b11000 &
1#
#260000
0#
#265000
b1 !
b1 (
b1000 1
1-
b0 0
b1 .
b0 /
b100 2
b11001 &
1#
#270000
0#
#275000
b10 !
b10 (
b1000 1
1-
b1 0
b10 .
b1 /
b100 2
b11010 &
1#
#280000
0#
#285000
b100 !
b100 (
b1000 1
1-
b10 0
b100 .
b10 /
b100 2
b11011 &
1#
#290000
0#
#295000
b1000 !
b1000 (
b1000 1
1-
b11 0
b1000 .
b11 /
b100 2
b11100 &
1#
#300000
0#
#305000
b1 !
b1 (
b1000 1
1-
b0 0
b1 .
b0 /
b100 2
b11101 &
1#
#310000
0#
#315000
b10 !
b10 (
b1000 1
1-
b1 0
b10 .
b1 /
b100 2
b11110 &
1#
#320000
0#
#325000
b100 !
b100 (
b1000 1
1-
b10 0
b100 .
b10 /
b100 2
b11111 &
1#
#330000
0#
#335000
b1000 !
b1000 (
b1000 1
1-
b11 0
b1000 .
b11 /
b100 2
b100000 &
1#
#340000
0#
#345000
b1 !
b1 (
b1000 1
1-
b0 0
b1 .
b0 /
b100 2
b100001 &
1#
#350000
0#
#355000
b10 !
b10 (
b1000 1
1-
b1 0
b10 .
b1 /
b100 2
b100010 &
1#
#360000
0#
#365000
b100 !
b100 (
b1000 1
1-
b10 0
b100 .
b10 /
b100 2
b100011 &
1#
#370000
0#
#375000
b1000 !
b1000 (
b1000 1
1-
b11 0
b1000 .
b11 /
b100 2
b100100 &
1#
#380000
0#
#385000
b1 !
b1 (
b1000 1
1-
b0 0
b1 .
b0 /
b100 2
b100101 &
1#
#390000
0#
#395000
b10 !
b10 (
b1000 1
1-
b1 0
b10 .
b1 /
b100 2
b100110 &
1#
#400000
0#
#405000
b100 !
b100 (
b1000 1
1-
b10 0
b100 .
b10 /
b100 2
b100111 &
1#
#410000
0#
#415000
b1000 !
b1000 (
b1000 1
1-
b11 0
b1000 .
b11 /
b100 2
b101000 &
1#
#420000
0#
#425000
b1 !
b1 (
b1000 1
1-
b0 0
b1 .
b0 /
b100 2
b101001 &
1#
#430000
b100 4
b101010 &
0#
#435000
b10 !
b10 (
b1000 1
1-
b1 0
b10 .
b1 /
b100 2
b101011 &
1#
#440000
b1000 !
b1000 (
b11 0
b1000 1
1-
b1000 .
b10001000 *
b1000 $
b1000 )
0#
#445000
b1000 1
1-
b11 0
b1000 .
b0 /
b100 2
b101100 &
1#
#450000
0#
#455000
b100 2
b101101 &
1#
#460000
0#
#465000
b100 2
b101110 &
1#
#470000
0#
#475000
b100 2
b101111 &
1#
#480000
0#
#485000
b100 2
b110000 &
1#
#490000
0#
#495000
b100 2
b110001 &
1#
#500000
0#
#505000
b100 2
b110010 &
1#
#510000
0#
#515000
b100 2
b110011 &
1#
#520000
0#
#525000
b100 2
b110100 &
1#
#530000
0#
#535000
b100 2
b110101 &
1#
#540000
b100 5
b110110 &
0#
#545000
b100 2
b110111 &
1#
#550000
b1 !
b1 (
b1000 1
1-
b0 0
b1 .
b10001 *
b1 $
b1 )
0#
#555000
b1000 1
1-
b0 0
b10000 .
b1 /
b100 2
b111000 &
1#
#560000
0#
#565000
b100 2
b111001 &
1#
#570000
0#
#575000
b100 2
b111010 &
1#
#580000
0#
#585000
b100 2
b111011 &
1#
#590000
0#
#595000
b100 2
b111100 &
1#
#600000
0#
#605000
b100 2
b111101 &
1#
#610000
0#
#615000
b100 2
b111110 &
1#
#620000
0#
#625000
b100 2
b111111 &
1#
#630000
0#
#635000
b100 2
b1000000 &
1#
#640000
0#
#645000
b100 2
b1000001 &
1#
#650000
b100 6
b1000010 &
0#
#655000
b100 2
b1000011 &
1#
#660000
b100 !
b100 (
b1000 1
1-
b10 0
b100 .
b1010101 *
b101 $
b101 )
0#
#665000
b1 !
b1 (
b1000 1
1-
b0 0
b10000 .
b11 /
b100 2
b1000100 &
1#
#670000
0#
#675000
b100 !
b100 (
b1000 1
1-
b10 0
b100 .
b1 /
b100 2
b1000101 &
1#
#680000
0#
#685000
b1 !
b1 (
b1000 1
1-
b0 0
b10000 .
b11 /
b100 2
b1000110 &
1#
#690000
0#
#695000
b100 !
b100 (
b1000 1
1-
b10 0
b100 .
b1 /
b100 2
b1000111 &
1#
#700000
0#
#705000
b1 !
b1 (
b1000 1
1-
b0 0
b10000 .
b11 /
b100 2
b1001000 &
1#
#710000
0#
#715000
b100 !
b100 (
b1000 1
1-
b10 0
b100 .
b1 /
b100 2
b1001001 &
1#
#720000
0#
#725000
b1 !
b1 (
b1000 1
1-
b0 0
b10000 .
b11 /
b100 2
b1001010 &
1#
#730000
0#
#735000
b100 !
b100 (
b1000 1
1-
b10 0
b100 .
b1 /
b100 2
b1001011 &
1#
#740000
0#
#745000
b1 !
b1 (
b1000 1
1-
b0 0
b10000 .
b11 /
b100 2
b1001100 &
1#
#750000
0#
#755000
b100 !
b100 (
b1000 1
1-
b10 0
b100 .
b1 /
b100 2
b1001101 &
1#
#760000
0#
#765000
b1 !
b1 (
b1000 1
1-
b0 0
b10000 .
b11 /
b100 2
b1001110 &
1#
#770000
0#
#775000
b100 !
b100 (
b1000 1
1-
b10 0
b100 .
b1 /
b100 2
b1001111 &
1#
#780000
0#
#785000
b1 !
b1 (
b1000 1
1-
b0 0
b10000 .
b11 /
b100 2
b1010000 &
1#
#790000
0#
#795000
b100 !
b100 (
b1000 1
1-
b10 0
b100 .
b1 /
b100 2
b1010001 &
1#
#800000
0#
#805000
b1 !
b1 (
b1000 1
1-
b0 0
b10000 .
b11 /
b100 2
b1010010 &
1#
#810000
0#
#815000
b100 !
b100 (
b1000 1
1-
b10 0
b100 .
b1 /
b100 2
b1010011 &
1#
#820000
0#
#825000
b1 !
b1 (
b1000 1
1-
b0 0
b10000 .
b11 /
b100 2
b1010100 &
1#
#830000
0#
#835000
b100 !
b100 (
b1000 1
1-
b10 0
b100 .
b1 /
b100 2
b1010101 &
1#
#840000
0#
#845000
b1 !
b1 (
b1000 1
1-
b0 0
b10000 .
b11 /
b100 2
b1010110 &
1#
#850000
0#
#855000
b100 !
b100 (
b1000 1
1-
b10 0
b100 .
b1 /
b100 2
b1010111 &
1#
#860000
b0 !
b0 (
b1000 1
0-
b1 0
b0 .
b0 *
b0 $
b0 )
b1011000 &
0#
#865000
b100 2
b1011001 &
1#
#870000
0#
#875000
b100 2
b1011010 &
1#
#880000
0#
#885000
b100 2
b1011011 &
1#
#890000
0#
#895000
b100 2
b1011100 &
1#
#900000
0#
#905000
b100 2
b1011101 &
1#
