07_floating_point/fp_adder.sv
// =============================================================================
// fp_adder.sv - IEEE 754 Single-Precision (32-bit) Floating-Point Adder
// =============================================================================
module fp_adder (
    input  logic [31:0] a,
    input  logic [31:0] b,
    output logic [31:0] result
);
    // ---- Unpack ----
    wire        sa = a[31], sb = b[31];
    wire  [7:0] ea = a[30:23], eb = b[30:23];
    wire [22:0] ma = a[22:0],  mb = b[22:0];

    wire a_nan  = (ea == 8'hFF) && (ma != 0);
    wire b_nan  = (eb == 8'hFF) && (mb != 0);
    wire a_inf  = (ea == 8'hFF) && (ma == 0);
    wire b_inf  = (eb == 8'hFF) && (mb == 0);
    wire a_zero = (ea == 8'h00) && (ma == 0);
    wire b_zero = (eb == 8'h00) && (mb == 0);

    // 24-bit significands (with implicit leading 1)
    wire [23:0] siga = (ea == 0) ? {1'b0, ma} : {1'b1, ma};
    wire [23:0] sigb = (eb == 0) ? {1'b0, mb} : {1'b1, mb};

    // ---- Align ----
    wire        a_bigger = (ea > eb) || ((ea == eb) && (siga >= sigb));
    wire  [7:0] exp_big  = a_bigger ? ea : eb;
    wire  [7:0] exp_sml  = a_bigger ? eb : ea;
    wire [23:0] sig_big  = a_bigger ? siga : sigb;
    wire [23:0] sig_sml  = a_bigger ? sigb : siga;
    wire        s_big    = a_bigger ? sa : sb;
    wire        s_sml    = a_bigger ? sb : sa;

    wire  [7:0] shamt  = exp_big - exp_sml;
    // Shift sig_sml right by shamt; use 48-bit extended to avoid losing bits
    // then take the upper 24 bits as the aligned value
    wire [47:0] sml_ext       = {sig_sml, 24'b0};
    wire [47:0] sml_shifted   = sml_ext >> shamt;
    wire [23:0] sig_sml_align = sml_shifted[47:24];

    // ---- Add/subtract ----
    wire same_sign = (s_big == s_sml);
    // 25-bit sum to capture carry/borrow
    wire [24:0] raw = same_sign ? ({1'b0, sig_big} + {1'b0, sig_sml_align})
                                : ({1'b0, sig_big} - {1'b0, sig_sml_align});

    // ---- Normalize ----
    // raw[24] = carry (overflow); otherwise leading 1 is somewhere in raw[23:0]
    // Expand to 48 bits for clean left-shifting
    wire [47:0] raw_ext = {23'b0, raw};  // leading 1 is at raw[24] or lower

    // Priority: find highest set bit in raw[24:0]
    wire [4:0] lz;    // # of leading zeros above the leading 1 in raw[24:0]
    assign lz = raw[24] ? 5'd0 :
                raw[23] ? 5'd1 :
                raw[22] ? 5'd2 :
                raw[21] ? 5'd3 :
                raw[20] ? 5'd4 :
                raw[19] ? 5'd5 :
                raw[18] ? 5'd6 :
                raw[17] ? 5'd7 :
                raw[16] ? 5'd8 :
                raw[15] ? 5'd9 :
                raw[14] ? 5'd10 :
                raw[13] ? 5'd11 :
                raw[12] ? 5'd12 :
                raw[11] ? 5'd13 :
                raw[10] ? 5'd14 :
                raw[9]  ? 5'd15 :
                raw[8]  ? 5'd16 :
                raw[7]  ? 5'd17 :
                raw[6]  ? 5'd18 :
                raw[5]  ? 5'd19 :
                raw[4]  ? 5'd20 :
                raw[3]  ? 5'd21 :
                raw[2]  ? 5'd22 :
                raw[1]  ? 5'd23 :
                raw[0]  ? 5'd24 : 5'd25;   // 25 = all zeros (result is 0)

    // After left-shifting raw by lz, the leading 1 is at bit 24.
    // The 23-bit mantissa is bits [23:1] of the shifted value (just below the leading 1).
    // raw_ext pads raw to 48 bits; after <<lz, norm[24] = leading 1, norm[23:1] = mantissa.
    wire [47:0] norm    = raw_ext << lz;
    wire [22:0] mant_out = norm[23:1];      // *** 23 bits immediately below the leading 1 ***

    // Exponent formula (derived from first principles):
    //   position p of leading 1 in raw = 24 - lz
    //   exp_out = exp_big - 23 + p = exp_big + 1 - lz
    wire [8:0] exp_adj = {1'b0, exp_big} + 9'd1 - {4'b0, lz};
    wire [7:0] exp_out = (raw == 0)  ? 8'h00 :
                         exp_adj[8]  ? 8'hFF :   // overflow -> inf
                                       exp_adj[7:0];

    // ---- Repack ----
    always_comb begin
        if (a_nan || b_nan)
            result = 32'h7FC00000;
        else if (a_inf && b_inf && (sa != sb))
            result = 32'h7FC00000;
        else if (a_inf) result = a;
        else if (b_inf) result = b;
        else if (a_zero) result = b;
        else if (b_zero) result = a;
        else if (raw == 0) result = 32'h00000000;
        else if (exp_out == 8'hFF) result = {s_big, 8'hFF, 23'h0};
        else result = {s_big, exp_out, mant_out};
    end
endmodule

07_floating_point/tb_fp_adder.sv
// =============================================================================
// tb_fp_adder.sv - Self-checking testbench for fp_adder
// All test vectors use pre-computed IEEE 754 hex bit patterns (bypassing
// Icarus's $realtobits limitation that always returns double-precision bits).
// =============================================================================
`timescale 1ns/1ps
module tb_fp_adder;

    logic [31:0] a, b, result;
    int errors = 0, checks = 0;
    fp_adder dut (.a(a), .b(b), .result(result));

    initial begin
        $dumpfile("fp_adder.vcd");
        $dumpvars(0, tb_fp_adder);
    end

    // Allow 2 ULP tolerance (truncation vs round-to-nearest)
    function automatic bit fp_close(input [31:0] got, exp);
        int diff;
        if (got[30:23]==8'hFF && got[22:0]!=0 && exp[30:23]==8'hFF && exp[22:0]!=0) return 1;
        if (got==exp) return 1;
        diff = $signed({1'b0, got}) - $signed({1'b0, exp});
        if (diff < 0) diff = -diff;
        return (diff <= 2);
    endfunction

    task automatic chk(input [31:0] av, bv, exp, input string lbl);
        a=av; b=bv; #1;
        checks++;
        if (!fp_close(result, exp)) begin
            $display("FAIL[%s]: a=%h b=%h got=%h exp=%h", lbl, av, bv, result, exp);
            errors++;
        end
    endtask

    initial begin
        // ---- Basic arithmetic (all values from Python: struct.pack('f',...)) ----
        chk(32'h3F800000, 32'h40000000, 32'h40400000, "1+2=3");
        chk(32'h3FC00000, 32'h40200000, 32'h40800000, "1.5+2.5=4");
        chk(32'hBF800000, 32'h3F800000, 32'h00000000, "-1+1=0");
        chk(32'h00000000, 32'h40A00000, 32'h40A00000, "0+5=5");
        chk(32'h42C80000, 32'h3A83126F, 32'h42C80083, "100+0.001");
        chk(32'h60AD78EC, 32'h60AD78EC, 32'h612D78EC, "1e20+1e20=2e20");
        chk(32'h1E3CE508, 32'h1E3CE508, 32'h1EBCE508, "1e-20+1e-20=2e-20");
        chk(32'hC0490FDB, 32'h40490FDB, 32'h00000000, "-pi+pi=0");
        chk(32'h40A00000, 32'hC0600000, 32'h3FC00000, "5+(-3.5)=1.5");
        chk(32'h3E4CCCCD, 32'h3DCCCCCD, 32'h3E99999A, "0.2+0.1~0.3");
        chk(32'h47C35000, 32'hC7C35000, 32'h00000000, "100k+(-100k)=0");
        chk(32'h461C4000, 32'h45FA0000, 32'h468CA000, "10000+8000=18000");
        chk(32'hBF800000, 32'hBF800000, 32'hC0000000, "-1+(-1)=-2");
        chk(32'h42480000, 32'h42480000, 32'h42C80000, "50+50=100");
        chk(32'h3F800000, 32'hBF000000, 32'h3F000000, "1+(-0.5)=0.5");
        chk(32'h43FA0000, 32'hC3C80000, 32'h42C80000, "500+(-400)=100");
        chk(32'h44898000, 32'h44898000, 32'h45098000, "1100+1100=2200");
        chk(32'h3727C5AC, 32'h36A7C5AC, 32'h377BA882, "tiny+smaller");

        // ---- Special values ----
        a=32'h7F800000; b=32'h3F800000; #1; checks++;  // +inf + 1.0 = +inf
        if (result!==32'h7F800000) begin $display("FAIL +inf+1=%h",result); errors++; end
        a=32'h7F800000; b=32'hFF800000; #1; checks++;  // +inf+(-inf) = NaN
        if (result[30:23]!==8'hFF || result[22:0]==0) begin $display("FAIL inf-inf=%h",result); errors++; end
        a=32'h7FC00000; b=32'h3F800000; #1; checks++;  // NaN+1 = NaN
        if (result[30:23]!==8'hFF || result[22:0]==0) begin $display("FAIL NaN+1=%h",result); errors++; end
        a=32'h00000000; b=32'h00000000; #1; checks++;  // 0+0=0
        if (result!==32'h00000000) begin $display("FAIL 0+0=%h",result); errors++; end

        $display("--------------------------------------------------");
        if (errors==0) $display("FP_ADDER: ALL %0d CHECKS PASSED", checks);
        else           $display("FP_ADDER: %0d ERRORS out of %0d checks", errors, checks);
        $display("--------------------------------------------------");
        #20 $finish;
    end
endmodule

07_floating_point/fp_adder.vcd
$date
	Thu Jul  2 01:57:51 2026
$end
$version
	Icarus Verilog
$end
$timescale
	1ps
$end
$scope module tb_fp_adder $end
$var wire 32 ! result [31:0] $end
$var reg 32 " a [31:0] $end
$var reg 32 # b [31:0] $end
$var integer 32 $ checks [31:0] $end
$var integer 32 % errors [31:0] $end
$scope function fp_close $end
$upscope $end
$scope module dut $end
$var wire 32 & a [31:0] $end
$var wire 1 ' a_bigger $end
$var wire 1 ( a_inf $end
$var wire 1 ) a_nan $end
$var wire 1 * a_zero $end
$var wire 32 + b [31:0] $end
$var wire 1 , b_inf $end
$var wire 1 - b_nan $end
$var wire 1 . b_zero $end
$var wire 1 / same_sign $end
$var wire 48 0 sml_shifted [47:0] $end
$var wire 48 1 sml_ext [47:0] $end
$var wire 24 2 sigb [23:0] $end
$var wire 24 3 siga [23:0] $end
$var wire 24 4 sig_sml_align [23:0] $end
$var wire 24 5 sig_sml [23:0] $end
$var wire 24 6 sig_big [23:0] $end
$var wire 8 7 shamt [7:0] $end
$var wire 1 8 sb $end
$var wire 1 9 sa $end
$var wire 1 : s_sml $end
$var wire 1 ; s_big $end
$var wire 48 < raw_ext [47:0] $end
$var wire 25 = raw [24:0] $end
$var wire 48 > norm [47:0] $end
$var wire 23 ? mb [22:0] $end
$var wire 23 @ mant_out [22:0] $end
$var wire 23 A ma [22:0] $end
$var wire 5 B lz [4:0] $end
$var wire 8 C exp_sml [7:0] $end
$var wire 8 D exp_out [7:0] $end
$var wire 8 E exp_big [7:0] $end
$var wire 9 F exp_adj [8:0] $end
$var wire 8 G eb [7:0] $end
$var wire 8 H ea [7:0] $end
$var reg 32 I result [31:0] $end
$upscope $end
$scope task chk $end
$upscope $end
$upscope $end
$enddefinitions $end
$comment Show the parameter values. $end
$dumpall
$end
#0
$dumpvars
b1000000010000000000000000000000 I
b1111111 H
b10000000 G
b10000000 F
b10000000 E
b10000000 D
b1111111 C
b1 B
b0 A
b10000000000000000000000 @
b0 ?
b1100000000000000000000000 >
b110000000000000000000000 =
b110000000000000000000000 <
0;
0:
09
08
b1 7
b100000000000000000000000 6
b100000000000000000000000 5
b10000000000000000000000 4
b100000000000000000000000 3
b100000000000000000000000 2
b100000000000000000000000000000000000000000000000 1
b10000000000000000000000000000000000000000000000 0
1/
0.
0-
0,
b1000000000000000000000000000000 +
0*
0)
0(
0'
b111111100000000000000000000000 &
b0 %
b0 $
b1000000000000000000000000000000 #
b111111100000000000000000000000 "
b1000000010000000000000000000000 !
$end
#1000
b10000001 D
b1000000100000000000000000000000 !
b1000000100000000000000000000000 I
b10000001 F
b0 B
b0 @
b1000000000000000000000000 >
b1000000000000000000000000 <
b1000000000000000000000000 =
b11000000000000000000000 4
b101000000000000000000000 6
b11000000000000000000000000000000000000000000000 0
b110000000000000000000000000000000000000000000000 1
b110000000000000000000000 5
b101000000000000000000000 2
b110000000000000000000000 3
b1000000000000000000000 ?
b10000000000000000000000 A
b1000000001000000000000000000000 #
b1000000001000000000000000000000 +
b111111110000000000000000000000 "
b111111110000000000000000000000 &
b1 $
#2000
b11001 B
b0 D
b0 !
b0 I
1;
b0 >
b0 <
b0 =
1'
b100000000000000000000000 4
b100000000000000000000000 6
0/
b100000000000000000000000000000000000000000000000 1
b100000000000000000000000 5
b100000000000000000000000000000000000000000000000 0
b0 7
b1100111 F
b1111111 E
b100000000000000000000000 2
0:
b100000000000000000000000 3
b1111111 G
b0 ?
19
b0 A
b111111100000000000000000000000 #
b111111100000000000000000000000 +
b10111111100000000000000000000000 "
b10111111100000000000000000000000 &
b10 $
#3000
b1000000000000000000000 @
b1 B
b10000001 D
b1010000000000000000000000 >
b101000000000000000000000 <
b101000000000000000000000 =
b0 1
b0 5
1/
b1000000101000000000000000000000 !
b1000000101000000000000000000000 I
b101000000000000000000000 6
0'
b0 4
b0 C
b101000000000000000000000 2
0;
1*
b0 3
b0 0
b10000001 7
b10000001 F
b10000001 E
b10000001 G
b1000000000000000000000 ?
09
b0 H
b1000000101000000000000000000000 #
b1000000101000000000000000000000 +
b0 "
b0 &
b11 $
#4000
b10000101 D
b10010000000000010000011 @
b1100100000000000100000110 >
b110010000000000010000011 <
b110010000000000010000011 =
b10000011 4
b110010000000000000000000 6
b10000011000100100110111100000000 0
b100000110001001001101111000000000000000000000000 1
b100000110001001001101111 5
b10000101 F
b10000101 E
b100000110001001001101111 2
1'
b10000 7
b1110101 C
0*
b110010000000000000000000 3
b1110101 G
b110001001001101111 ?
b1000010110010000000000010000011 !
b1000010110010000000000010000011 I
b10000101 H
b10010000000000000000000 A
b111010100000110001001001101111 #
b111010100000110001001001101111 +
b1000010110010000000000000000000 "
b1000010110010000000000000000000 &
b100 $
#5000
b1100001001011010111100011101100 !
b1100001001011010111100011101100 I
b0 B
b11000010 D
b1011010111100011101100 @
b1010110101111000111011000 >
b1010110101111000111011000 <
b1010110101111000111011000 =
b101011010111100011101100000000000000000000000000 1
b101011010111100011101100 5
b101011010111100011101100 4
b101011010111100011101100 6
b11000001 C
b101011010111100011101100 2
b101011010111100011101100000000000000000000000000 0
b0 7
b11000010 F
b11000001 E
b101011010111100011101100 3
b11000001 G
b1011010111100011101100 ?
b11000001 H
b1011010111100011101100 A
b1100000101011010111100011101100 #
b1100000101011010111100011101100 +
b1100000101011010111100011101100 "
b1100000101011010111100011101100 &
b101 $
#6000
b11110101111001110010100001000 !
b11110101111001110010100001000 I
b111101 D
b1111001110010100001000 @
b101111001110010100001000 4
b1011110011100101000010000 >
b1011110011100101000010000 <
b1011110011100101000010000 =
b101111001110010100001000000000000000000000000000 1
b101111001110010100001000 5
b101111001110010100001000 6
b111100 C
b101111001110010100001000 2
b101111001110010100001000000000000000000000000000 0
b0 7
b111101 F
b111100 E
b101111001110010100001000 3
b111100 G
b1111001110010100001000 ?
b111100 H
b1111001110010100001000 A
b11110001111001110010100001000 #
b11110001111001110010100001000 +
b11110001111001110010100001000 "
b11110001111001110010100001000 &
b110 $
#7000
b11001 B
b0 D
b0 @
b110010010000111111011011 4
b0 >
b0 <
b0 =
b110010010000111111011011000000000000000000000000 1
b110010010000111111011011 5
0/
b0 !
b0 I
b110010010000111111011011 6
b10000000 C
b110010010000111111011011 2
1;
b110010010000111111011011000000000000000000000000 0
b0 7
b1101000 F
b10000000 E
b110010010000111111011011 3
b10000000 G
b10010010000111111011011 ?
19
b10000000 H
b10010010000111111011011 A
b1000000010010010000111111011011 #
b1000000010010010000111111011011 +
b11000000010010010000111111011011 "
b11000000010010010000111111011011 &
b111 $
#8000
b10000000000000000000000 @
b11 B
b111111110000000000000000000000 !
b111111110000000000000000000000 I
b1111111 D
b1100000000000000000000000 >
b1100000000000000000000 <
b1100000000000000000000 =
b111000000000000000000000000000000000000000000000 1
b111000000000000000000000 5
b11100000000000000000000 4
b101000000000000000000000 6
1:
b111000000000000000000000 2
0;
b11100000000000000000000000000000000000000000000 0
b1 7
b1111111 F
b10000001 E
b101000000000000000000000 3
18
b11000000000000000000000 ?
09
b10000001 H
b1000000000000000000000 A
b11000000011000000000000000000000 #
b11000000011000000000000000000000 +
b1000000101000000000000000000000 "
b1000000101000000000000000000000 &
b1000 $
#9000
b111110100110011001100110011001 !
b111110100110011001100110011001 I
b0 B
b1111101 D
b110011001100110011001 @
b11001100110011001100110 4
b1001100110011001100110011 >
b1001100110011001100110011 <
b1001100110011001100110011 =
1/
b110011001100110011001101000000000000000000000000 1
b110011001100110011001101 5
b110011001100110011001101 6
0:
b1111011 C
b110011001100110011001101 2
b11001100110011001100110100000000000000000000000 0
b1 7
b1111101 F
b1111100 E
b110011001100110011001101 3
08
b1111011 G
b10011001100110011001101 ?
b1111100 H
b10011001100110011001101 A
b111101110011001100110011001101 #
b111101110011001100110011001101 +
b111110010011001100110011001101 "
b111110010011001100110011001101 &
b1001 $
#10000
b11001 B
b0 !
b0 I
b0 D
b0 @
b0 >
b0 <
b0 =
0/
b110000110101000000000000000000000000000000000000 1
b110000110101000000000000 5
b110000110101000000000000 4
b110000110101000000000000 6
1:
b10001111 C
b110000110101000000000000 2
b110000110101000000000000000000000000000000000000 0
b0 7
b1110111 F
b10001111 E
b110000110101000000000000 3
18
b10001111 G
b10000110101000000000000 ?
b10001111 H
b10000110101000000000000 A
b11000111110000110101000000000000 #
b11000111110000110101000000000000 +
b1000111110000110101000000000000 "
b1000111110000110101000000000000 &
b1010 $
#11000
b11001010000000000000 @
b0 B
b1000110100011001010000000000000 !
b1000110100011001010000000000000 I
b10001101 D
b1000110010100000000000000 >
b1000110010100000000000000 <
b1000110010100000000000000 =
1/
b111110100000000000000000000000000000000000000000 1
b111110100000000000000000 5
b11111010000000000000000 4
b100111000100000000000000 6
0:
b10001011 C
b111110100000000000000000 2
b11111010000000000000000000000000000000000000000 0
b1 7
b10001101 F
b10001100 E
b100111000100000000000000 3
08
b10001011 G
b11110100000000000000000 ?
b10001100 H
b111000100000000000000 A
b1000101111110100000000000000000 #
b1000101111110100000000000000000 +
b1000110000111000100000000000000 "
b1000110000111000100000000000000 &
b1011 $
#12000
b10000000 D
b0 @
b1000000000000000000000000 >
b1000000000000000000000000 <
b1000000000000000000000000 =
b100000000000000000000000000000000000000000000000 1
b100000000000000000000000 5
b100000000000000000000000 4
b100000000000000000000000 6
1:
b11000000000000000000000000000000 !
b11000000000000000000000000000000 I
b1111111 C
b100000000000000000000000 2
1;
1'
b100000000000000000000000000000000000000000000000 0
b0 7
b10000000 F
b1111111 E
b100000000000000000000000 3
18
b1111111 G
b0 ?
19
b1111111 H
b0 A
b10111111100000000000000000000000 #
b10111111100000000000000000000000 +
b10111111100000000000000000000000 "
b10111111100000000000000000000000 &
b1100 $
#13000
b10000101 D
b10010000000000000000000 @
b110010000000000000000000 4
b1100100000000000000000000 >
b1100100000000000000000000 <
b1100100000000000000000000 =
b110010000000000000000000000000000000000000000000 1
b110010000000000000000000 5
b110010000000000000000000 6
0:
b1000010110010000000000000000000 !
b1000010110010000000000000000000 I
b10000100 C
b110010000000000000000000 2
0;
b110010000000000000000000000000000000000000000000 0
b0 7
b10000101 F
b10000100 E
b110010000000000000000000 3
08
b10000100 G
b10010000000000000000000 ?
09
b10000100 H
b10010000000000000000000 A
b1000010010010000000000000000000 #
b1000010010010000000000000000000 +
b1000010010010000000000000000000 "
b1000010010010000000000000000000 &
b1101 $
#14000
b111111000000000000000000000000 !
b111111000000000000000000000000 I
b10 B
b1111110 D
b0 @
b1000000000000000000000000 >
b10000000000000000000000 <
b10000000000000000000000 =
0/
b100000000000000000000000000000000000000000000000 1
b100000000000000000000000 5
b10000000000000000000000 4
b100000000000000000000000 6
1:
b1111110 C
b100000000000000000000000 2
b10000000000000000000000000000000000000000000000 0
b1 7
b1111110 F
b1111111 E
b100000000000000000000000 3
18
b1111110 G
b0 ?
b1111111 H
b0 A
b10111111000000000000000000000000 #
b10111111000000000000000000000000 +
b111111100000000000000000000000 "
b111111100000000000000000000000 &
b1110 $
#15000
b11 B
b1000010110010000000000000000000 !
b1000010110010000000000000000000 I
b10000101 D
b10010000000000000000000 @
b1100100000000000000000000 >
b1100100000000000000000 <
b1100100000000000000000 =
b110010000000000000000000000000000000000000000000 1
b110010000000000000000000 5
b110010000000000000000000 4
b111110100000000000000000 6
b10000111 C
b110010000000000000000000 2
b110010000000000000000000000000000000000000000000 0
b0 7
b10000101 F
b10000111 E
b111110100000000000000000 3
b10000111 G
b10010000000000000000000 ?
b10000111 H
b11110100000000000000000 A
b11000011110010000000000000000000 #
b11000011110010000000000000000000 +
b1000011111110100000000000000000 "
b1000011111110100000000000000000 &
b1111 $
#16000
b1000101000010011000000000000000 !
b1000101000010011000000000000000 I
b0 B
b10001010 D
b10011000000000000000 @
b100010011000000000000000 4
b1000100110000000000000000 >
b1000100110000000000000000 <
b1000100110000000000000000 =
1/
b100010011000000000000000000000000000000000000000 1
b100010011000000000000000 5
b100010011000000000000000 6
0:
b10001001 C
b100010011000000000000000 2
1'
b100010011000000000000000000000000000000000000000 0
b0 7
b10001010 F
b10001001 E
b100010011000000000000000 3
08
b10001001 G
b10011000000000000000 ?
b10001001 H
b10011000000000000000 A
b1000100100010011000000000000000 #
b1000100100010011000000000000000 +
b1000100100010011000000000000000 "
b1000100100010011000000000000000 &
b10000 $
#17000
b110111011110111010100010000010 !
b110111011110111010100010000010 I
b1 B
b1101110 D
b11110111010100010000010 @
b1111101110101000100000100 >
b111110111010100010000010 <
b111110111010100010000010 =
b101001111100010110101100000000000000000000000000 1
b101001111100010110101100 5
b10100111110001011010110 4
b101001111100010110101100 6
b1101101 C
b101001111100010110101100 2
b10100111110001011010110000000000000000000000000 0
b1 7
b1101110 F
b1101110 E
b101001111100010110101100 3
b1101101 G
b1001111100010110101100 ?
b1101110 H
b1001111100010110101100 A
b110110101001111100010110101100 #
b110110101001111100010110101100 +
b110111001001111100010110101100 "
b110111001001111100010110101100 &
b10001 $
#18000
b11111111 D
b0 @
b1000000000000000000000000 >
b100000000000000000000000 <
b100000000000000000000000 =
b100000000000000000000000000000000000000000000000 1
b100000000000000000000000 5
b0 4
b1111111100000000000000000000000 !
b1111111100000000000000000000000 I
b100000000000000000000000 6
b1111111 C
b100000000000000000000000 2
b0 0
b10000000 7
b11111111 F
b11111111 E
1(
b100000000000000000000000 3
b1111111 G
b0 ?
b11111111 H
b0 A
b111111100000000000000000000000 #
b111111100000000000000000000000 +
b1111111100000000000000000000000 "
b1111111100000000000000000000000 &
b10010 $
#19000
b11100111 F
b11001 B
b0 D
b0 >
b0 <
b0 =
0/
b1111111110000000000000000000000 !
b1111111110000000000000000000000 I
b100000000000000000000000 4
1:
1,
b100000000000000000000000000000000000000000000000 0
b0 7
b11111111 C
18
b11111111 G
b11111111100000000000000000000000 #
b11111111100000000000000000000000 +
b10011 $
#20000
b10000000000000000000000 @
b11111111 F
b1 B
b11111111 D
b1100000000000000000000000 >
b110000000000000000000000 <
b110000000000000000000000 =
1/
b0 4
b110000000000000000000000 6
0:
0,
b0 0
b10000000 7
b1111111 C
1)
0(
b110000000000000000000000 3
08
b1111111 G
b10000000000000000000000 A
b111111100000000000000000000000 #
b111111100000000000000000000000 +
b1111111110000000000000000000000 "
b1111111110000000000000000000000 &
b10100 $
#21000
b11001 B
b0 @
b0 D
b0 >
b0 <
b0 =
b0 1
b0 5
b0 !
b0 I
b0 6
1.
b0 2
b0 0
b0 C
1'
b0 7
b111101000 F
b0 E
0)
1*
b0 3
b0 G
b0 H
b0 A
b0 #
b0 +
b0 "
b0 &
b10101 $
#22000
b10110 $
