03_cdc_techniques/sync_2ff.sv
// =============================================================================
// sync_2ff.sv - Two-Flip-Flop Synchronizer
// -----------------------------------------------------------------------------
// The most basic CDC (Clock Domain Crossing) primitive. Used to bring a
// SINGLE-BIT, SLOWLY-CHANGING (relative to the destination clock) signal
// safely into a new clock domain.
//
// Why 2 flops and not 1? A single flop sampling an asynchronous input can go
// METASTABLE (its output hovers between 0 and 1 for an unbounded time) if the
// input changes right at the sampling clock edge. The first flop is allowed
// to go metastable; giving it a full clock period to resolve before the
// SECOND flop samples it makes the probability of the metastability
// propagating any further astronomically small (this is the "MTBF" -- Mean
// Time Between Failures -- calculation every CDC checklist references).
//
// Rules this module follows (and any real synchronizer must follow):
//   1. Only ONE bit crosses per synchronizer instance (multi-bit buses need
//      gray coding or a handshake -- see async_fifo.sv / handshake_sync.sv).
//   2. No combinational logic on the signal between the two flops.
//   3. The source flop's output is never touched by anything else "along
//      the way" (no fan-out taps between ff1 and ff2).
// =============================================================================
module sync_2ff #(
    parameter int STAGES = 2                  // 2 is the common minimum; 3 for very high-speed/noisy designs
) (
    input  logic clk,        // destination clock domain
    input  logic rst_n,
    input  logic async_in,   // signal coming from another (or asynchronous) clock domain
    output logic sync_out
);

    (* ASYNC_REG = "TRUE" *)                  // synthesis attribute: tells the tool to place these flops
    logic [STAGES-1:0] sync_ff;               // close together and not optimize/retime them

    always_ff @(posedge clk or negedge rst_n) begin
        if (!rst_n) sync_ff <= '0;
        else        sync_ff <= {sync_ff[STAGES-2:0], async_in};
    end

    assign sync_out = sync_ff[STAGES-1];

endmodule

03_cdc_techniques/pulse_sync.sv
// =============================================================================
// pulse_sync.sv - Pulse Synchronizer (toggle + 2-flop-sync + edge detect)
// -----------------------------------------------------------------------------
// Problem: a plain 2-flop synchronizer works great for a LEVEL signal, but a
// single-cycle PULSE in a fast clock domain can be completely missed by a
// slower destination clock (it can come and go between two destination edges).
//
// Fix: convert the pulse into a LEVEL change (a toggle flip-flop), synchronize
// that level with an ordinary 2-flop synchronizer (safe, since it's now a
// slowly-changing level, not a pulse), then detect the EDGE of the
// synchronized toggle to regenerate a clean single-cycle pulse in the
// destination clock domain.
//
//   src_pulse ---> [toggle FF] ---> level change ---> [2FF sync] ---> [edge
//   detect] ---> dst_pulse (exactly one dst_clk cycle wide)
//
// Constraint: pulses in the source domain must be spaced at least 2 source
// clock periods apart (must let the toggle flop settle) or they can be
// missed/coalesced -- this synchronizer guarantees every pulse is SEEN, not
// that back-to-back pulses stay distinguishable if they arrive faster than
// the destination can keep up.
// =============================================================================
module pulse_sync (
    input  logic src_clk,
    input  logic src_rst_n,
    input  logic src_pulse,      // single src_clk-cycle pulse to be transferred

    input  logic dst_clk,
    input  logic dst_rst_n,
    output logic dst_pulse       // single dst_clk-cycle pulse, in the destination domain
);

    // ---------------- Source domain: toggle on every pulse ----------------
    logic toggle_ff;
    always_ff @(posedge src_clk or negedge src_rst_n) begin
        if (!src_rst_n) toggle_ff <= 1'b0;
        else if (src_pulse) toggle_ff <= ~toggle_ff;
    end

    // ---------------- Cross to destination domain (safe: it's now a level) ----------------
    logic sync_toggle;
    sync_2ff #(.STAGES(2)) u_sync (
        .clk(dst_clk), .rst_n(dst_rst_n),
        .async_in(toggle_ff), .sync_out(sync_toggle)
    );

    // ---------------- Edge-detect the synchronized toggle to regenerate a pulse ----------------
    logic sync_toggle_d;
    always_ff @(posedge dst_clk or negedge dst_rst_n) begin
        if (!dst_rst_n) sync_toggle_d <= 1'b0;
        else            sync_toggle_d <= sync_toggle;
    end

    assign dst_pulse = sync_toggle ^ sync_toggle_d;   // XOR = "it just changed" = one pulse per toggle edge

endmodule

03_cdc_techniques/tb_pulse_sync.sv
// =============================================================================
// tb_pulse_sync.sv
// =============================================================================
`timescale 1ns/1ps
module tb_pulse_sync;

    logic src_clk = 0, dst_clk = 0;
    logic src_rst_n, dst_rst_n;
    logic src_pulse, dst_pulse;

    int src_pulse_count = 0;
    int dst_pulse_count = 0;

    pulse_sync dut (
        .src_clk(src_clk), .src_rst_n(src_rst_n), .src_pulse(src_pulse),
        .dst_clk(dst_clk), .dst_rst_n(dst_rst_n), .dst_pulse(dst_pulse)
    );

    always #2.5 src_clk = ~src_clk;   // fast domain, 5ns period
    always #9.0 dst_clk = ~dst_clk;   // slow domain, 18ns period

    initial begin
        $dumpfile("pulse_sync.vcd");
        $dumpvars(0, tb_pulse_sync);
    end

    // Count pulses seen on each side
    always @(posedge src_clk) if (src_rst_n && src_pulse) src_pulse_count++;
    always @(posedge dst_clk) if (dst_rst_n && dst_pulse) dst_pulse_count++;

    initial begin
        src_pulse = 0;
        src_rst_n = 0; dst_rst_n = 0;
        repeat (3) @(posedge src_clk);
        repeat (3) @(posedge dst_clk);
        src_rst_n = 1; dst_rst_n = 1;
        @(posedge src_clk);

        // Send 15 well-spaced pulses (spaced >= 4 src clocks apart, safely
        // obeying the "let the toggle settle" constraint). Framing the pulse
        // between two negedges guarantees it is stable across exactly one
        // posedge, with no race against the posedge-triggered counter below.
        for (int i = 0; i < 15; i++) begin
            @(negedge src_clk);
            src_pulse = 1;
            @(negedge src_clk);
            src_pulse = 0;
            repeat (4) @(posedge src_clk);   // gap between pulses
        end

        // Let the last pulse fully propagate through the synchronizer
        repeat (10) @(posedge dst_clk);

        $display("--------------------------------------------------");
        $display("PULSE_SYNC: src_pulse_count=%0d dst_pulse_count=%0d", src_pulse_count, dst_pulse_count);
        if (src_pulse_count == dst_pulse_count && src_pulse_count == 15)
            $display("PULSE_SYNC: ALL PULSES CORRECTLY TRANSFERRED (PASS)");
        else
            $display("PULSE_SYNC: MISMATCH -- FAIL");
        $display("--------------------------------------------------");
        #100 $finish;
    end
endmodule

03_cdc_techniques/pulse_sync.vcd
$date
	Wed Jul  1 19:50:16 2026
$end
$version
	Icarus Verilog
$end
$timescale
	1ps
$end
$scope module tb_pulse_sync $end
$var wire 1 ! dst_pulse $end
$var reg 1 " dst_clk $end
$var reg 1 # dst_rst_n $end
$var reg 1 $ src_clk $end
$var reg 1 % src_pulse $end
$var reg 1 & src_rst_n $end
$var integer 32 ' dst_pulse_count [31:0] $end
$var integer 32 ( src_pulse_count [31:0] $end
$scope module dut $end
$var wire 1 " dst_clk $end
$var wire 1 ! dst_pulse $end
$var wire 1 # dst_rst_n $end
$var wire 1 $ src_clk $end
$var wire 1 % src_pulse $end
$var wire 1 & src_rst_n $end
$var wire 1 ) sync_toggle $end
$var reg 1 * sync_toggle_d $end
$var reg 1 + toggle_ff $end
$scope module u_sync $end
$var wire 1 + async_in $end
$var wire 1 " clk $end
$var wire 1 # rst_n $end
$var wire 1 ) sync_out $end
$var parameter 32 , STAGES $end
$var reg 2 - sync_ff [1:0] $end
$upscope $end
$upscope $end
$scope begin $ivl_for_loop0 $end
$var integer 32 . i [31:0] $end
$upscope $end
$upscope $end
$enddefinitions $end
$comment Show the parameter values. $end
$dumpall
b10 ,
$end
#0
$dumpvars
b0 .
b0 -
0+
0*
0)
b0 (
b0 '
0&
0%
0$
0#
0"
0!
$end
#2500
1$
#5000
0$
#7500
1$
#9000
1"
#10000
0$
#12500
1$
#15000
0$
#17500
1$
#18000
0"
#20000
0$
#22500
1$
#25000
0$
#27000
1"
#27500
1$
#30000
0$
#32500
1$
#35000
0$
#36000
0"
#37500
1$
#40000
0$
#42500
1$
#45000
0$
1"
#47500
1$
#50000
0$
#52500
1$
#54000
0"
#55000
0$
#57500
1$
#60000
0$
#62500
1$
#63000
1#
1&
1"
#65000
0$
#67500
1$
#70000
1%
0$
#72000
0"
#72500
1+
b1 (
1$
#75000
0%
0$
#77500
1$
#80000
0$
#81000
b1 -
1"
#82500
1$
#85000
0$
#87500
1$
#90000
0$
0"
#92500
b1 .
1$
#95000
1%
0$
#97500
0+
b10 (
1$
#99000
1!
1)
b10 -
1"
#100000
0%
0$
#102500
1$
#105000
0$
#107500
1$
#108000
0"
#110000
0$
#112500
1$
#115000
0$
#117000
0)
1*
b0 -
b1 '
1"
#117500
b10 .
1$
#120000
1%
0$
#122500
1+
b11 (
1$
#125000
0%
0$
#126000
0"
#127500
1$
#130000
0$
#132500
1$
#135000
0!
b1 -
0*
b10 '
0$
1"
#137500
1$
#140000
0$
#142500
b11 .
1$
#144000
0"
#145000
1%
0$
#147500
0+
b100 (
1$
#150000
0%
0$
#152500
1$
#153000
1!
1)
b10 -
1"
#155000
0$
#157500
1$
#160000
0$
#162000
0"
#162500
1$
#165000
0$
#167500
b100 .
1$
#170000
1%
0$
#171000
0)
1!
b0 -
1*
b11 '
1"
#172500
1+
b101 (
1$
#175000
0%
0$
#177500
1$
#180000
0$
0"
#182500
1$
#185000
0$
#187500
1$
#189000
0!
0*
b1 -
b100 '
1"
#190000
0$
#192500
b101 .
1$
#195000
1%
0$
#197500
0+
b110 (
1$
#198000
0"
#200000
0%
0$
#202500
1$
#205000
0$
#207000
1!
1)
b10 -
1"
#207500
1$
#210000
0$
#212500
1$
#215000
0$
#216000
0"
#217500
b110 .
1$
#220000
1%
0$
#222500
1+
b111 (
1$
#225000
0)
1*
b1 -
0%
b101 '
0$
1"
#227500
1$
#230000
0$
#232500
1$
#234000
0"
#235000
0$
#237500
1$
#240000
0$
#242500
b111 .
1$
#243000
1)
1!
b11 -
0*
b110 '
1"
#245000
1%
0$
#247500
0+
b1000 (
1$
#250000
0%
0$
#252000
0"
#252500
1$
#255000
0$
#257500
1$
#260000
0$
#261000
0!
1*
b10 -
b111 '
1"
#262500
1$
#265000
0$
#267500
b1000 .
1$
#270000
1%
0$
0"
#272500
1+
b1001 (
1$
#275000
0%
0$
#277500
1$
#279000
1!
0)
b1 -
1"
#280000
0$
#282500
1$
#285000
0$
#287500
1$
#288000
0"
#290000
0$
#292500
b1001 .
1$
#295000
1%
0$
#297000
1)
0*
b11 -
b1000 '
1"
#297500
0+
b1010 (
1$
#300000
0%
0$
#302500
1$
#305000
0$
#306000
0"
#307500
1$
#310000
0$
#312500
1$
#315000
0!
b10 -
1*
b1001 '
0$
1"
#317500
b1010 .
1$
#320000
1%
0$
#322500
1+
b1011 (
1$
#324000
0"
#325000
0%
0$
#327500
1$
#330000
0$
#332500
1$
#333000
1!
0)
b1 -
1"
#335000
0$
#337500
1$
#340000
0$
#342000
0"
#342500
b1011 .
1$
#345000
1%
0$
#347500
0+
b1100 (
1$
#350000
0%
0$
#351000
1)
1!
b10 -
0*
b1010 '
1"
#352500
1$
#355000
0$
#357500
1$
#360000
0$
0"
#362500
1$
#365000
0$
#367500
b1100 .
1$
#369000
0)
1*
b0 -
b1011 '
1"
#370000
1%
0$
#372500
1+
b1101 (
1$
#375000
0%
0$
#377500
1$
#378000
0"
#380000
0$
#382500
1$
#385000
0$
#387000
0!
b1 -
0*
b1100 '
1"
#387500
1$
#390000
0$
#392500
b1101 .
1$
#395000
1%
0$
#396000
0"
#397500
0+
b1110 (
1$
#400000
0%
0$
#402500
1$
#405000
1!
1)
b10 -
0$
1"
#407500
1$
#410000
0$
#412500
1$
#414000
0"
#415000
0$
#417500
b1110 .
1$
#420000
1%
0$
#422500
1+
b1111 (
1$
#423000
0)
1!
b1 -
1*
b1101 '
1"
#425000
0%
0$
#427500
1$
#430000
0$
#432000
0"
#432500
1$
#435000
0$
#437500
1$
#440000
0$
#441000
1)
0*
b11 -
b1110 '
1"
#442500
b1111 .
1$
#445000
0$
#447500
1$
#450000
0$
0"
#452500
1$
#455000
0$
#457500
1$
#459000
0!
1*
b1111 '
1"
