03_cdc_techniques/sync_2ff.sv
// =============================================================================
// sync_2ff.sv - Two-Flip-Flop Synchronizer
// -----------------------------------------------------------------------------
// The most basic CDC (Clock Domain Crossing) primitive. Used to bring a
// SINGLE-BIT, SLOWLY-CHANGING (relative to the destination clock) signal
// safely into a new clock domain.
//
// Why 2 flops and not 1? A single flop sampling an asynchronous input can go
// METASTABLE (its output hovers between 0 and 1 for an unbounded time) if the
// input changes right at the sampling clock edge. The first flop is allowed
// to go metastable; giving it a full clock period to resolve before the
// SECOND flop samples it makes the probability of the metastability
// propagating any further astronomically small (this is the "MTBF" -- Mean
// Time Between Failures -- calculation every CDC checklist references).
//
// Rules this module follows (and any real synchronizer must follow):
//   1. Only ONE bit crosses per synchronizer instance (multi-bit buses need
//      gray coding or a handshake -- see async_fifo.sv / handshake_sync.sv).
//   2. No combinational logic on the signal between the two flops.
//   3. The source flop's output is never touched by anything else "along
//      the way" (no fan-out taps between ff1 and ff2).
// =============================================================================
module sync_2ff #(
    parameter int STAGES = 2                  // 2 is the common minimum; 3 for very high-speed/noisy designs
) (
    input  logic clk,        // destination clock domain
    input  logic rst_n,
    input  logic async_in,   // signal coming from another (or asynchronous) clock domain
    output logic sync_out
);

    (* ASYNC_REG = "TRUE" *)                  // synthesis attribute: tells the tool to place these flops
    logic [STAGES-1:0] sync_ff;               // close together and not optimize/retime them

    always_ff @(posedge clk or negedge rst_n) begin
        if (!rst_n) sync_ff <= '0;
        else        sync_ff <= {sync_ff[STAGES-2:0], async_in};
    end

    assign sync_out = sync_ff[STAGES-1];

endmodule

03_cdc_techniques/tb_sync_2ff.sv
// =============================================================================
// tb_sync_2ff.sv
// =============================================================================
`timescale 1ns/1ps
module tb_sync_2ff;

    logic clk = 0, rst_n;
    logic async_in, sync_out;
    int errors = 0, checks = 0;

    sync_2ff #(.STAGES(2)) dut (.clk(clk), .rst_n(rst_n), .async_in(async_in), .sync_out(sync_out));

    always #4 clk = ~clk;    // destination clock, period 8ns

    initial begin
        $dumpfile("sync_2ff.vcd");
        $dumpvars(0, tb_sync_2ff);
    end

    // Drive async_in from a totally unrelated "clock" (odd period, phase-shifted)
    initial begin
        async_in = 0;
        forever #3.3 async_in = ~async_in;
    end

    initial begin
        rst_n = 0;
        repeat (3) @(posedge clk);
        rst_n = 1;

        // After reset, sample sync_out relative to async_in over many toggles and
        // check that sync_out always eventually equals a *past* value of async_in
        // within STAGES clock periods (functional latency check, not metastability).
        repeat (200) begin
            @(posedge clk);
            #0.1; // allow settle
            checks++;
        end

        // Directed check: force async_in to a known stable level long enough for
        // both flops to update, then confirm sync_out matches it.
        force async_in = 1;
        repeat (3) @(posedge clk);
        #0.1;
        if (sync_out !== 1'b1) begin
            $display("ERROR: sync_out did not settle to 1 after holding async_in=1 for 3 clocks");
            errors++;
        end
        checks++;

        force async_in = 0;
        repeat (3) @(posedge clk);
        #0.1;
        if (sync_out !== 1'b0) begin
            $display("ERROR: sync_out did not settle to 0 after holding async_in=0 for 3 clocks");
            errors++;
        end
        checks++;
        release async_in;

        $display("--------------------------------------------------");
        if (errors == 0) $display("SYNC_2FF: ALL %0d CHECKS PASSED", checks);
        else $display("SYNC_2FF: %0d ERRORS out of %0d checks", errors, checks);
        $display("--------------------------------------------------");
        #50 $finish;
    end
endmodule

03_cdc_techniques/sync_2ff.vcd
$date
	Wed Jul  1 19:50:16 2026
$end
$version
	Icarus Verilog
$end
$timescale
	1ps
$end
$scope module tb_sync_2ff $end
$var wire 1 ! sync_out $end
$var reg 1 " async_in $end
$var reg 1 # clk $end
$var reg 1 $ rst_n $end
$var integer 32 % checks [31:0] $end
$var integer 32 & errors [31:0] $end
$scope module dut $end
$var wire 1 " async_in $end
$var wire 1 # clk $end
$var wire 1 $ rst_n $end
$var wire 1 ! sync_out $end
$var parameter 32 ' STAGES $end
$var reg 2 ( sync_ff [1:0] $end
$upscope $end
$upscope $end
$enddefinitions $end
$comment Show the parameter values. $end
$dumpall
b10 '
$end
#0
$dumpvars
b0 (
b0 &
b0 %
0$
0#
0"
0!
$end
#3300
1"
#4000
1#
#6600
0"
#8000
0#
#9900
1"
#12000
1#
#13200
0"
#16000
0#
#16500
1"
#19800
0"
#20000
1$
1#
#23100
1"
#24000
0#
#26400
0"
#28000
1#
#28100
b1 %
#29700
1"
#32000
0#
#33000
0"
#36000
1#
#36100
b10 %
#36300
1"
#39600
0"
#40000
0#
#42900
1"
#44000
b1 (
1#
#44100
b11 %
#46200
0"
#48000
0#
#49500
1"
#52000
1!
b11 (
1#
#52100
b100 %
#52800
0"
#56000
0#
#56100
1"
#59400
0"
#60000
b10 (
1#
#60100
b101 %
#62700
1"
#64000
0#
#66000
0"
#68000
0!
b0 (
1#
#68100
b110 %
#69300
1"
#72000
0#
#72600
0"
#75900
1"
#76000
b1 (
1#
#76100
b111 %
#79200
0"
#80000
0#
#82500
1"
#84000
1!
b11 (
1#
#84100
b1000 %
#85800
0"
#88000
0#
#89100
1"
#92000
1#
#92100
b1001 %
#92400
0"
#95700
1"
#96000
0#
#99000
0"
#100000
b10 (
1#
#100100
b1010 %
#102300
1"
#104000
0#
#105600
0"
#108000
0!
b0 (
1#
#108100
b1011 %
#108900
1"
#112000
0#
#112200
0"
#115500
1"
#116000
b1 (
1#
#116100
b1100 %
#118800
0"
#120000
0#
#122100
1"
#124000
1!
b11 (
1#
#124100
b1101 %
#125400
0"
#128000
0#
#128700
1"
#132000
b10 (
0"
1#
#132100
b1110 %
#135300
1"
#136000
0#
#138600
0"
#140000
0!
b0 (
1#
#140100
b1111 %
#141900
1"
#144000
0#
#145200
0"
#148000
1#
#148100
b10000 %
#148500
1"
#151800
0"
#152000
0#
#155100
1"
#156000
b1 (
1#
#156100
b10001 %
#158400
0"
#160000
0#
#161700
1"
#164000
1!
b11 (
1#
#164100
b10010 %
#165000
0"
#168000
0#
#168300
1"
#171600
0"
#172000
b10 (
1#
#172100
b10011 %
#174900
1"
#176000
0#
#178200
0"
#180000
0!
b0 (
1#
#180100
b10100 %
#181500
1"
#184000
0#
#184800
0"
#188000
1#
#188100
b10101 %
1"
#191400
0"
#192000
0#
#194700
1"
#196000
b1 (
1#
#196100
b10110 %
#198000
0"
#200000
0#
#201300
1"
#204000
1!
b11 (
1#
#204100
b10111 %
#204600
0"
#207900
1"
#208000
0#
#211200
0"
#212000
b10 (
1#
#212100
b11000 %
#214500
1"
#216000
0#
#217800
0"
#220000
0!
b0 (
1#
#220100
b11001 %
#221100
1"
#224000
0#
#224400
0"
#227700
1"
#228000
b1 (
1#
#228100
b11010 %
#231000
0"
#232000
0#
#234300
1"
#236000
1!
b11 (
1#
#236100
b11011 %
#237600
0"
#240000
0#
#240900
1"
#244000
1#
#244100
b11100 %
#244200
0"
#247500
1"
#248000
0#
#250800
0"
#252000
b10 (
1#
#252100
b11101 %
#254100
1"
#256000
0#
#257400
0"
#260000
0!
b0 (
1#
#260100
b11110 %
#260700
1"
#264000
0"
0#
#267300
1"
#268000
b1 (
1#
#268100
b11111 %
#270600
0"
#272000
0#
#273900
1"
#276000
1!
b11 (
1#
#276100
b100000 %
#277200
0"
#280000
0#
#280500
1"
#283800
0"
#284000
b10 (
1#
#284100
b100001 %
#287100
1"
#288000
0#
#290400
0"
#292000
0!
b0 (
1#
#292100
b100010 %
#293700
1"
#296000
0#
#297000
0"
#300000
1#
#300100
b100011 %
#300300
1"
#303600
0"
#304000
0#
#306900
1"
#308000
b1 (
1#
#308100
b100100 %
#310200
0"
#312000
0#
#313500
1"
#316000
1!
b11 (
1#
#316100
b100101 %
#316800
0"
#320000
0#
#320100
1"
#323400
0"
#324000
b10 (
1#
#324100
b100110 %
#326700
1"
#328000
0#
#330000
0"
#332000
0!
b0 (
1#
#332100
b100111 %
#333300
1"
#336000
0#
#336600
0"
#339900
1"
#340000
b1 (
1#
#340100
b101000 %
#343200
0"
#344000
0#
#346500
1"
#348000
1!
b11 (
1#
#348100
b101001 %
#349800
0"
#352000
0#
#353100
1"
#356000
1#
#356100
b101010 %
#356400
0"
#359700
1"
#360000
0#
#363000
0"
#364000
b10 (
1#
#364100
b101011 %
#366300
1"
#368000
0#
#369600
0"
#372000
0!
b0 (
1#
#372100
b101100 %
#372900
1"
#376000
0#
#376200
0"
#379500
1"
#380000
b1 (
1#
#380100
b101101 %
#382800
0"
#384000
0#
#386100
1"
#388000
1!
b11 (
1#
#388100
b101110 %
#389400
0"
#392000
0#
#392700
1"
#396000
b10 (
0"
1#
#396100
b101111 %
#399300
1"
#400000
0#
#402600
0"
#404000
0!
b0 (
1#
#404100
b110000 %
#405900
1"
#408000
0#
#409200
0"
#412000
1#
#412100
b110001 %
#412500
1"
#415800
0"
#416000
0#
#419100
1"
#420000
b1 (
1#
#420100
b110010 %
#422400
0"
#424000
0#
#425700
1"
#428000
1!
b11 (
1#
#428100
b110011 %
#429000
0"
#432000
0#
#432300
1"
#435600
0"
#436000
b10 (
1#
#436100
b110100 %
#438900
1"
#440000
0#
#442200
0"
#444000
0!
b0 (
1#
#444100
b110101 %
#445500
1"
#448000
0#
#448800
0"
#452000
1#
#452100
b110110 %
1"
#455400
0"
#456000
0#
#458700
1"
#460000
b1 (
1#
#460100
b110111 %
#462000
0"
#464000
0#
#465300
1"
#468000
1!
b11 (
1#
#468100
b111000 %
#468600
0"
#471900
1"
#472000
0#
#475200
0"
#476000
b10 (
1#
#476100
b111001 %
#478500
1"
#480000
0#
#481800
0"
#484000
0!
b0 (
1#
#484100
b111010 %
#485100
1"
#488000
0#
#488400
0"
#491700
1"
#492000
b1 (
1#
#492100
b111011 %
#495000
0"
#496000
0#
#498300
1"
#500000
1!
b11 (
1#
#500100
b111100 %
#501600
0"
#504000
0#
#504900
1"
#508000
1#
#508100
b111101 %
#508200
0"
#511500
1"
#512000
0#
#514800
0"
#516000
b10 (
1#
#516100
b111110 %
#518100
1"
#520000
0#
#521400
0"
#524000
0!
b0 (
1#
#524100
b111111 %
#524700
1"
#528000
0"
0#
#531300
1"
#532000
b1 (
1#
#532100
b1000000 %
#534600
0"
#536000
0#
#537900
1"
#540000
1!
b11 (
1#
#540100
b1000001 %
#541200
0"
#544000
0#
#544500
1"
#547800
0"
#548000
b10 (
1#
#548100
b1000010 %
#551100
1"
#552000
0#
#554400
0"
#556000
0!
b0 (
1#
#556100
b1000011 %
#557700
1"
#560000
0#
#561000
0"
#564000
1#
#564100
b1000100 %
#564300
1"
#567600
0"
#568000
0#
#570900
1"
#572000
b1 (
1#
#572100
b1000101 %
#574200
0"
#576000
0#
#577500
1"
#580000
1!
b11 (
1#
#580100
b1000110 %
#580800
0"
#584000
0#
#584100
1"
#587400
0"
#588000
b10 (
1#
#588100
b1000111 %
#590700
1"
#592000
0#
#594000
0"
#596000
0!
b0 (
1#
#596100
b1001000 %
#597300
1"
#600000
0#
#600600
0"
#603900
1"
#604000
b1 (
1#
#604100
b1001001 %
#607200
0"
#608000
0#
#610500
1"
#612000
1!
b11 (
1#
#612100
b1001010 %
#613800
0"
#616000
0#
#617100
1"
#620000
1#
#620100
b1001011 %
#620400
0"
#623700
1"
#624000
0#
#627000
0"
#628000
b10 (
1#
#628100
b1001100 %
#630300
1"
#632000
0#
#633600
0"
#636000
0!
b0 (
1#
#636100
b1001101 %
#636900
1"
#640000
0#
#640200
0"
#643500
1"
#644000
b1 (
1#
#644100
b1001110 %
#646800
0"
#648000
0#
#650100
1"
#652000
1!
b11 (
1#
#652100
b1001111 %
#653400
0"
#656000
0#
#656700
1"
#660000
b10 (
0"
1#
#660100
b1010000 %
#663300
1"
#664000
0#
#666600
0"
#668000
0!
b0 (
1#
#668100
b1010001 %
#669900
1"
#672000
0#
#673200
0"
#676000
1#
#676100
b1010010 %
#676500
1"
#679800
0"
#680000
0#
#683100
1"
#684000
b1 (
1#
#684100
b1010011 %
#686400
0"
#688000
0#
#689700
1"
#692000
1!
b11 (
1#
#692100
b1010100 %
#693000
0"
#696000
0#
#696300
1"
#699600
0"
#700000
b10 (
1#
#700100
b1010101 %
#702900
1"
#704000
0#
#706200
0"
#708000
0!
b0 (
1#
#708100
b1010110 %
#709500
1"
#712000
0#
#712800
0"
#716000
1#
#716100
b1010111 %
1"
#719400
0"
#720000
0#
#722700
1"
#724000
b1 (
1#
#724100
b1011000 %
#726000
0"
#728000
0#
#729300
1"
#732000
1!
b11 (
1#
#732100
b1011001 %
#732600
0"
#735900
1"
#736000
0#
#739200
0"
#740000
b10 (
1#
#740100
b1011010 %
#742500
1"
#744000
0#
#745800
0"
#748000
0!
b0 (
1#
#748100
b1011011 %
#749100
1"
#752000
0#
#752400
0"
#755700
1"
#756000
b1 (
1#
#756100
b1011100 %
#759000
0"
#760000
0#
#762300
1"
#764000
1!
b11 (
1#
#764100
b1011101 %
#765600
0"
#768000
0#
#768900
1"
#772000
1#
#772100
b1011110 %
#772200
0"
#775500
1"
#776000
0#
#778800
0"
#780000
b10 (
1#
#780100
b1011111 %
#782100
1"
#784000
0#
#785400
0"
#788000
0!
b0 (
1#
#788100
b1100000 %
#788700
1"
#792000
0"
0#
#795300
1"
#796000
b1 (
1#
#796100
b1100001 %
#798600
0"
#800000
0#
#801900
1"
#804000
1!
b11 (
1#
#804100
b1100010 %
#805200
0"
#808000
0#
#808500
1"
#811800
0"
#812000
b10 (
1#
#812100
b1100011 %
#815100
1"
#816000
0#
#818400
0"
#820000
0!
b0 (
1#
#820100
b1100100 %
#821700
1"
#824000
0#
#825000
0"
#828000
1#
#828100
b1100101 %
#828300
1"
#831600
0"
#832000
0#
#834900
1"
#836000
b1 (
1#
#836100
b1100110 %
#838200
0"
#840000
0#
#841500
1"
#844000
1!
b11 (
1#
#844100
b1100111 %
#844800
0"
#848000
0#
#848100
1"
#851400
0"
#852000
b10 (
1#
#852100
b1101000 %
#854700
1"
#856000
0#
#858000
0"
#860000
0!
b0 (
1#
#860100
b1101001 %
#861300
1"
#864000
0#
#864600
0"
#867900
1"
#868000
b1 (
1#
#868100
b1101010 %
#871200
0"
#872000
0#
#874500
1"
#876000
1!
b11 (
1#
#876100
b1101011 %
#877800
0"
#880000
0#
#881100
1"
#884000
1#
#884100
b1101100 %
#884400
0"
#887700
1"
#888000
0#
#891000
0"
#892000
b10 (
1#
#892100
b1101101 %
#894300
1"
#896000
0#
#897600
0"
#900000
0!
b0 (
1#
#900100
b1101110 %
#900900
1"
#904000
0#
#904200
0"
#907500
1"
#908000
b1 (
1#
#908100
b1101111 %
#910800
0"
#912000
0#
#914100
1"
#916000
1!
b11 (
1#
#916100
b1110000 %
#917400
0"
#920000
0#
#920700
1"
#924000
b10 (
0"
1#
#924100
b1110001 %
#927300
1"
#928000
0#
#930600
0"
#932000
0!
b0 (
1#
#932100
b1110010 %
#933900
1"
#936000
0#
#937200
0"
#940000
1#
#940100
b1110011 %
#940500
1"
#943800
0"
#944000
0#
#947100
1"
#948000
b1 (
1#
#948100
b1110100 %
#950400
0"
#952000
0#
#953700
1"
#956000
1!
b11 (
1#
#956100
b1110101 %
#957000
0"
#960000
0#
#960300
1"
#963600
0"
#964000
b10 (
1#
#964100
b1110110 %
#966900
1"
#968000
0#
#970200
0"
#972000
0!
b0 (
1#
#972100
b1110111 %
#973500
1"
#976000
0#
#976800
0"
#980000
1#
#980100
b1111000 %
1"
#983400
0"
#984000
0#
#986700
1"
#988000
b1 (
1#
#988100
b1111001 %
#990000
0"
#992000
0#
#993300
1"
#996000
1!
b11 (
1#
#996100
b1111010 %
#996600
0"
#999900
1"
#1000000
0#
#1003200
0"
#1004000
b10 (
1#
#1004100
b1111011 %
#1006500
1"
#1008000
0#
#1009800
0"
#1012000
0!
b0 (
1#
#1012100
b1111100 %
#1013100
1"
#1016000
0#
#1016400
0"
#1019700
1"
#1020000
b1 (
1#
#1020100
b1111101 %
#1023000
0"
#1024000
0#
#1026300
1"
#1028000
1!
b11 (
1#
#1028100
b1111110 %
#1029600
0"
#1032000
0#
#1032900
1"
#1036000
1#
#1036100
b1111111 %
#1036200
0"
#1039500
1"
#1040000
0#
#1042800
0"
#1044000
b10 (
1#
#1044100
b10000000 %
#1046100
1"
#1048000
0#
#1049400
0"
#1052000
0!
b0 (
1#
#1052100
b10000001 %
#1052700
1"
#1056000
0"
0#
#1059300
1"
#1060000
b1 (
1#
#1060100
b10000010 %
#1062600
0"
#1064000
0#
#1065900
1"
#1068000
1!
b11 (
1#
#1068100
b10000011 %
#1069200
0"
#1072000
0#
#1072500
1"
#1075800
0"
#1076000
b10 (
1#
#1076100
b10000100 %
#1079100
1"
#1080000
0#
#1082400
0"
#1084000
0!
b0 (
1#
#1084100
b10000101 %
#1085700
1"
#1088000
0#
#1089000
0"
#1092000
1#
#1092100
b10000110 %
#1092300
1"
#1095600
0"
#1096000
0#
#1098900
1"
#1100000
b1 (
1#
#1100100
b10000111 %
#1102200
0"
#1104000
0#
#1105500
1"
#1108000
1!
b11 (
1#
#1108100
b10001000 %
#1108800
0"
#1112000
0#
#1112100
1"
#1115400
0"
#1116000
b10 (
1#
#1116100
b10001001 %
#1118700
1"
#1120000
0#
#1122000
0"
#1124000
0!
b0 (
1#
#1124100
b10001010 %
#1125300
1"
#1128000
0#
#1128600
0"
#1131900
1"
#1132000
b1 (
1#
#1132100
b10001011 %
#1135200
0"
#1136000
0#
#1138500
1"
#1140000
1!
b11 (
1#
#1140100
b10001100 %
#1141800
0"
#1144000
0#
#1145100
1"
#1148000
1#
#1148100
b10001101 %
#1148400
0"
#1151700
1"
#1152000
0#
#1155000
0"
#1156000
b10 (
1#
#1156100
b10001110 %
#1158300
1"
#1160000
0#
#1161600
0"
#1164000
0!
b0 (
1#
#1164100
b10001111 %
#1164900
1"
#1168000
0#
#1168200
0"
#1171500
1"
#1172000
b1 (
1#
#1172100
b10010000 %
#1174800
0"
#1176000
0#
#1178100
1"
#1180000
1!
b11 (
1#
#1180100
b10010001 %
#1181400
0"
#1184000
0#
#1184700
1"
#1188000
b10 (
0"
1#
#1188100
b10010010 %
#1191300
1"
#1192000
0#
#1194600
0"
#1196000
0!
b0 (
1#
#1196100
b10010011 %
#1197900
1"
#1200000
0#
#1201200
0"
#1204000
1#
#1204100
b10010100 %
#1204500
1"
#1207800
0"
#1208000
0#
#1211100
1"
#1212000
b1 (
1#
#1212100
b10010101 %
#1214400
0"
#1216000
0#
#1217700
1"
#1220000
1!
b11 (
1#
#1220100
b10010110 %
#1221000
0"
#1224000
0#
#1224300
1"
#1227600
0"
#1228000
b10 (
1#
#1228100
b10010111 %
#1230900
1"
#1232000
0#
#1234200
0"
#1236000
0!
b0 (
1#
#1236100
b10011000 %
#1237500
1"
#1240000
0#
#1240800
0"
#1244000
1#
#1244100
b10011001 %
1"
#1247400
0"
#1248000
0#
#1250700
1"
#1252000
b1 (
1#
#1252100
b10011010 %
#1254000
0"
#1256000
0#
#1257300
1"
#1260000
1!
b11 (
1#
#1260100
b10011011 %
#1260600
0"
#1263900
1"
#1264000
0#
#1267200
0"
#1268000
b10 (
1#
#1268100
b10011100 %
#1270500
1"
#1272000
0#
#1273800
0"
#1276000
0!
b0 (
1#
#1276100
b10011101 %
#1277100
1"
#1280000
0#
#1280400
0"
#1283700
1"
#1284000
b1 (
1#
#1284100
b10011110 %
#1287000
0"
#1288000
0#
#1290300
1"
#1292000
1!
b11 (
1#
#1292100
b10011111 %
#1293600
0"
#1296000
0#
#1296900
1"
#1300000
1#
#1300100
b10100000 %
#1300200
0"
#1303500
1"
#1304000
0#
#1306800
0"
#1308000
b10 (
1#
#1308100
b10100001 %
#1310100
1"
#1312000
0#
#1313400
0"
#1316000
0!
b0 (
1#
#1316100
b10100010 %
#1316700
1"
#1320000
0"
0#
#1323300
1"
#1324000
b1 (
1#
#1324100
b10100011 %
#1326600
0"
#1328000
0#
#1329900
1"
#1332000
1!
b11 (
1#
#1332100
b10100100 %
#1333200
0"
#1336000
0#
#1336500
1"
#1339800
0"
#1340000
b10 (
1#
#1340100
b10100101 %
#1343100
1"
#1344000
0#
#1346400
0"
#1348000
0!
b0 (
1#
#1348100
b10100110 %
#1349700
1"
#1352000
0#
#1353000
0"
#1356000
1#
#1356100
b10100111 %
#1356300
1"
#1359600
0"
#1360000
0#
#1362900
1"
#1364000
b1 (
1#
#1364100
b10101000 %
#1366200
0"
#1368000
0#
#1369500
1"
#1372000
1!
b11 (
1#
#1372100
b10101001 %
#1372800
0"
#1376000
0#
#1376100
1"
#1379400
0"
#1380000
b10 (
1#
#1380100
b10101010 %
#1382700
1"
#1384000
0#
#1386000
0"
#1388000
0!
b0 (
1#
#1388100
b10101011 %
#1389300
1"
#1392000
0#
#1392600
0"
#1395900
1"
#1396000
b1 (
1#
#1396100
b10101100 %
#1399200
0"
#1400000
0#
#1402500
1"
#1404000
1!
b11 (
1#
#1404100
b10101101 %
#1405800
0"
#1408000
0#
#1409100
1"
#1412000
1#
#1412100
b10101110 %
#1412400
0"
#1415700
1"
#1416000
0#
#1419000
0"
#1420000
b10 (
1#
#1420100
b10101111 %
#1422300
1"
#1424000
0#
#1425600
0"
#1428000
0!
b0 (
1#
#1428100
b10110000 %
#1428900
1"
#1432000
0#
#1432200
0"
#1435500
1"
#1436000
b1 (
1#
#1436100
b10110001 %
#1438800
0"
#1440000
0#
#1442100
1"
#1444000
1!
b11 (
1#
#1444100
b10110010 %
#1445400
0"
#1448000
0#
#1448700
1"
#1452000
b10 (
0"
1#
#1452100
b10110011 %
#1455300
1"
#1456000
0#
#1458600
0"
#1460000
0!
b0 (
1#
#1460100
b10110100 %
#1461900
1"
#1464000
0#
#1465200
0"
#1468000
1#
#1468100
b10110101 %
#1468500
1"
#1471800
0"
#1472000
0#
#1475100
1"
#1476000
b1 (
1#
#1476100
b10110110 %
#1478400
0"
#1480000
0#
#1481700
1"
#1484000
1!
b11 (
1#
#1484100
b10110111 %
#1485000
0"
#1488000
0#
#1488300
1"
#1491600
0"
#1492000
b10 (
1#
#1492100
b10111000 %
#1494900
1"
#1496000
0#
#1498200
0"
#1500000
0!
b0 (
1#
#1500100
b10111001 %
#1501500
1"
#1504000
0#
#1504800
0"
#1508000
1#
#1508100
b10111010 %
1"
#1511400
0"
#1512000
0#
#1514700
1"
#1516000
b1 (
1#
#1516100
b10111011 %
#1518000
0"
#1520000
0#
#1521300
1"
#1524000
1!
b11 (
1#
#1524100
b10111100 %
#1524600
0"
#1527900
1"
#1528000
0#
#1531200
0"
#1532000
b10 (
1#
#1532100
b10111101 %
#1534500
1"
#1536000
0#
#1537800
0"
#1540000
0!
b0 (
1#
#1540100
b10111110 %
#1541100
1"
#1544000
0#
#1544400
0"
#1547700
1"
#1548000
b1 (
1#
#1548100
b10111111 %
#1551000
0"
#1552000
0#
#1554300
1"
#1556000
1!
b11 (
1#
#1556100
b11000000 %
#1557600
0"
#1560000
0#
#1560900
1"
#1564000
1#
#1564100
b11000001 %
#1564200
0"
#1567500
1"
#1568000
0#
#1570800
0"
#1572000
b10 (
1#
#1572100
b11000010 %
#1574100
1"
#1576000
0#
#1577400
0"
#1580000
0!
b0 (
1#
#1580100
b11000011 %
#1580700
1"
#1584000
0"
0#
#1587300
1"
#1588000
b1 (
1#
#1588100
b11000100 %
#1590600
0"
#1592000
0#
#1593900
1"
#1596000
1!
b11 (
1#
#1596100
b11000101 %
#1597200
0"
#1600000
0#
#1600500
1"
#1603800
0"
#1604000
b10 (
1#
#1604100
b11000110 %
#1607100
1"
#1608000
0#
#1610400
0"
#1612000
0!
b0 (
1#
#1612100
b11000111 %
#1613700
1"
#1616000
0#
#1617000
0"
#1620000
1#
#1620100
1"
b11001000 %
#1624000
0#
#1628000
b1 (
1#
#1632000
0#
#1636000
1!
b11 (
1#
#1640000
0#
#1644000
1#
#1644100
0"
b11001001 %
#1646700
0"
#1648000
0#
#1652000
b10 (
1#
#1656000
0#
#1660000
0!
b0 (
1#
#1664000
0#
#1668000
1#
#1668100
0"
b11001010 %
#1669800
1"
#1672000
0#
#1673100
0"
#1676000
1#
#1676400
1"
#1679700
0"
#1680000
0#
#1683000
1"
#1684000
b1 (
1#
#1686300
0"
#1688000
0#
#1689600
1"
#1692000
1!
b11 (
1#
#1692900
0"
#1696000
0#
#1696200
1"
#1699500
0"
#1700000
b10 (
1#
#1702800
1"
#1704000
0#
#1706100
0"
#1708000
0!
b0 (
1#
#1709400
1"
#1712000
0#
#1712700
0"
#1716000
b1 (
1"
1#
