04_clock_dividers/clk_div_even.sv
// =============================================================================
// clk_div_even.sv - Clock Divider for EVEN divide ratios (50% duty cycle)
// -----------------------------------------------------------------------------
// For an even divisor N, a single counter that toggles the output every N/2
// input clock cycles gives a perfect 50% duty cycle output at f_in / N.
//
// Example: N=4 -> count 0,1 with clk_out=0, then 2,3 with clk_out=1, repeat.
// This is the simplest possible clock divider and is fully synchronous.
//
// NOTE: this produces a DIVIDED CLOCK, i.e. a new clock domain. In real ASIC
// design you would typically prefer a "clock enable" pulse gating logic on
// the ORIGINAL fast clock (so all logic stays on one clock tree) rather than
// physically dividing the clock, specifically to avoid clock-tree/skew
// headaches. This module is presented both ways: clk_out (divided clock,
// for teaching / simple FPGA use) and enable_out (a clock-enable pulse,
// asserted for exactly one f_in cycle at the divided-clock rate -- the
// ASIC-friendly version).
// =============================================================================
module clk_div_even #(
    parameter int DIV = 4                      // must be even and >= 2
) (
    input  logic clk_in,
    input  logic rst_n,
    output logic clk_out,       // divided clock, 50% duty cycle, frequency = f(clk_in)/DIV
    output logic enable_out     // ASIC-friendly alternative: 1-cycle-wide pulse at the divided rate
);

    localparam int HALF = DIV / 2;
    localparam int CW   = $clog2(HALF);

    logic [CW-1:0] count;

    always_ff @(posedge clk_in or negedge rst_n) begin
        if (!rst_n) begin
            count   <= '0;
            clk_out <= 1'b0;
        end else begin
            if (count == HALF - 1) begin
                count   <= '0;
                clk_out <= ~clk_out;
            end else begin
                count <= count + 1'b1;
            end
        end
    end

    // enable_out: pulses for exactly one clk_in cycle, once per full DIV period
    // (aligned to the rising edge of clk_out, i.e. once every DIV input cycles)
    always_ff @(posedge clk_in or negedge rst_n) begin
        if (!rst_n) enable_out <= 1'b0;
        else        enable_out <= (count == HALF - 1) && !clk_out;
    end

endmodule

04_clock_dividers/tb_clk_div_even.sv
// =============================================================================
// tb_clk_div_even.sv
// =============================================================================
`timescale 1ns/1ps
module tb_clk_div_even;

    localparam int DIV = 4;
    logic clk_in = 0, rst_n;
    logic clk_out, enable_out;
    int errors = 0, checks = 0;

    clk_div_even #(.DIV(DIV)) dut (.clk_in(clk_in), .rst_n(rst_n), .clk_out(clk_out), .enable_out(enable_out));

    localparam real TIN = 4.0;
    always #(TIN/2) clk_in = ~clk_in;

    initial begin
        $dumpfile("clk_div_even.vcd");
        $dumpvars(0, tb_clk_div_even);
    end

    time t_rise0, t_rise1, t_fall0;

    initial begin
        rst_n = 0;
        repeat (4) @(posedge clk_in);
        rst_n = 1;

        // Measure period between two consecutive rising edges of clk_out
        @(posedge clk_out);
        t_rise0 = $time;
        @(negedge clk_out);
        t_fall0 = $time;
        @(posedge clk_out);
        t_rise1 = $time;

        $display("clk_out period measured = %0t (expected %0t)", t_rise1 - t_rise0, DIV * TIN);
        checks++;
        if ((t_rise1 - t_rise0) != DIV * TIN) begin
            $display("ERROR: period mismatch");
            errors++;
        end

        $display("clk_out high time = %0t (expected %0t, i.e. 50%% duty)", t_fall0 - t_rise0, (DIV*TIN)/2);
        checks++;
        if ((t_fall0 - t_rise0) != (DIV*TIN)/2) begin
            $display("ERROR: duty cycle mismatch");
            errors++;
        end

        // Run several more periods and check consistency + count enable_out pulses
        begin
            int enable_count = 0;
            time t_start = $time;
            for (int i = 0; i < 20; i++) @(posedge clk_in) if (enable_out) enable_count++;
            $display("enable_out pulses seen in 20 clk_in cycles = %0d (expected ~%0d)", enable_count, 20/DIV);
            checks++;
            if (enable_count != 20/DIV) begin
                $display("ERROR: enable_out pulse count mismatch");
                errors++;
            end
        end

        $display("--------------------------------------------------");
        if (errors == 0) $display("CLK_DIV_EVEN (DIV=%0d): ALL %0d CHECKS PASSED", DIV, checks);
        else $display("CLK_DIV_EVEN: %0d ERRORS out of %0d checks", errors, checks);
        $display("--------------------------------------------------");
        #50 $finish;
    end
endmodule

04_clock_dividers/clk_div_even.vcd
$date
	Wed Jul  1 19:51:44 2026
$end
$version
	Icarus Verilog
$end
$timescale
	1ps
$end
$scope module tb_clk_div_even $end
$var wire 1 ! enable_out $end
$var wire 1 " clk_out $end
$var parameter 32 # DIV $end
$var real 1 $ TIN $end
$var reg 1 % clk_in $end
$var reg 1 & rst_n $end
$var reg 64 ' t_fall0 [63:0] $end
$var reg 64 ( t_rise0 [63:0] $end
$var reg 64 ) t_rise1 [63:0] $end
$var integer 32 * checks [31:0] $end
$var integer 32 + errors [31:0] $end
$scope module dut $end
$var wire 1 % clk_in $end
$var wire 1 & rst_n $end
$var parameter 32 , CW $end
$var parameter 32 - DIV $end
$var parameter 32 . HALF $end
$var reg 1 " clk_out $end
$var reg 1 / count $end
$var reg 1 ! enable_out $end
$upscope $end
$scope begin $unm_blk_11 $end
$var reg 64 0 t_start [63:0] $end
$var integer 32 1 enable_count [31:0] $end
$scope begin $ivl_for_loop0 $end
$var integer 32 2 i [31:0] $end
$upscope $end
$upscope $end
$upscope $end
$enddefinitions $end
$comment Show the parameter values. $end
$dumpall
b10 .
b100 -
b1 ,
r4 $
b100 #
$end
#0
$dumpvars
b0 2
b0 1
b0 0
0/
b0 +
b0 *
bx )
bx (
bx '
0&
0%
0"
0!
$end
#2000
1%
#4000
0%
#6000
1%
#8000
0%
#10000
1%
#12000
0%
#14000
1/
1&
1%
#16000
0%
#18000
b10010 (
1!
1"
0/
1%
#20000
0%
#22000
1/
0!
1%
#24000
0%
#26000
b11010 '
0"
0/
1%
#28000
0%
#30000
1/
1%
#32000
0%
#34000
b10 *
b100010 )
1!
1"
0/
1%
#36000
0%
#38000
1/
0!
b1 2
b1 1
1%
#40000
0%
#42000
0"
0/
b10 2
1%
#44000
0%
#46000
1/
b11 2
1%
#48000
0%
#50000
1!
1"
0/
b100 2
1%
#52000
0%
#54000
1/
0!
b101 2
b10 1
1%
#56000
0%
#58000
0"
0/
b110 2
1%
#60000
0%
#62000
1/
b111 2
1%
#64000
0%
#66000
1!
1"
0/
b1000 2
1%
#68000
0%
#70000
1/
0!
b1001 2
b11 1
1%
#72000
0%
#74000
0"
0/
b1010 2
1%
#76000
0%
#78000
1/
b1011 2
1%
#80000
0%
#82000
1!
1"
0/
b1100 2
1%
#84000
0%
#86000
1/
0!
b1101 2
b100 1
1%
#88000
0%
#90000
0"
0/
b1110 2
1%
#92000
0%
#94000
1/
b1111 2
1%
#96000
0%
#98000
1!
1"
0/
b10000 2
1%
#100000
0%
#102000
1/
0!
b10001 2
b101 1
1%
#104000
0%
#106000
0"
0/
b10010 2
1%
#108000
0%
#110000
1/
b10011 2
1%
#112000
0%
#114000
1!
1"
0/
b11 *
b10100 2
1%
#116000
0%
#118000
1/
0!
1%
#120000
0%
#122000
0"
0/
1%
#124000
0%
#126000
1/
1%
#128000
0%
#130000
1!
1"
0/
1%
#132000
0%
#134000
1/
0!
1%
#136000
0%
#138000
0"
0/
1%
#140000
0%
#142000
1/
1%
#144000
0%
#146000
1!
1"
0/
1%
#148000
0%
#150000
1/
0!
1%
#152000
0%
#154000
0"
0/
1%
#156000
0%
#158000
1/
1%
#160000
0%
#162000
1!
1"
0/
1%
