04_clock_dividers/clk_div_odd.sv
// =============================================================================
// clk_div_odd.sv - Clock Divider for ODD divide ratios (50% duty cycle)
// -----------------------------------------------------------------------------
// Dividing by an ODD number and still getting a clean 50% duty cycle is a
// classic ASIC/FPGA interview question, because the "obvious" single-counter
// approach (toggle at N/2) doesn't work when N/2 isn't a whole number.
//
// THE TRICK: use TWO counters counting the same modulus N -- one clocked on
// the POSEDGE of clk_in, one on the NEGEDGE -- so they are naturally offset
// from each other by exactly half an input clock period. Each counter drives
// a "high for the first half of the count" signal (using H = (N+1)/2, the
// same threshold for both). ANDing the two signals together yields an output
// that is high for exactly N/2 input-clock-periods' worth of time and low for
// the other half -- i.e. a mathematically perfect 50% duty cycle -- even
// though N itself is odd.
//
// Worked example for DIV=3 (H=2):
//   cnt_p (posedge):  0   1   2   0   1   2  ...
//   tmp1 = cnt_p<2:   1   1   0   1   1   0  ...
//   cnt_n (negedge, offset by half a cycle from cnt_p): ... 0  1  2  0 ...
//   tmp2 = cnt_n<2:      1     1     0     1  ...
//   clk_out = tmp1 & tmp2 ends up high for exactly 1.5 input periods and low
//   for exactly 1.5 input periods out of every 3-period cycle -- 50% duty.
// =============================================================================
module clk_div_odd #(
    parameter int DIV = 3                      // must be odd and >= 3
) (
    input  logic clk_in,
    input  logic rst_n,
    output logic clk_out
);

    localparam int H  = (DIV + 1) / 2;         // ceil(DIV/2)
    localparam int CW = $clog2(DIV);

    logic [CW-1:0] cnt_p;   // counts on the rising edge of clk_in
    logic [CW-1:0] cnt_n;   // counts on the falling edge of clk_in (naturally half-period offset)
    logic tmp1, tmp2;

    always_ff @(posedge clk_in or negedge rst_n) begin
        if (!rst_n)                cnt_p <= '0;
        else if (cnt_p == DIV - 1) cnt_p <= '0;
        else                       cnt_p <= cnt_p + 1'b1;
    end

    always_ff @(negedge clk_in or negedge rst_n) begin
        if (!rst_n)                cnt_n <= '0;
        else if (cnt_n == DIV - 1) cnt_n <= '0;
        else                       cnt_n <= cnt_n + 1'b1;
    end

    assign tmp1    = (cnt_p < H);
    assign tmp2    = (cnt_n < H);
    assign clk_out = tmp1 & tmp2;

endmodule

04_clock_dividers/tb_clk_div_odd.sv
// =============================================================================
// tb_clk_div_odd.sv
// =============================================================================
`timescale 1ns/1ps
module tb_clk_div_odd;

    localparam int DIV = 5;   // try an odd ratio
    logic clk_in = 0, rst_n;
    logic clk_out;
    int errors = 0, checks = 0;

    clk_div_odd #(.DIV(DIV)) dut (.clk_in(clk_in), .rst_n(rst_n), .clk_out(clk_out));

    localparam real TIN = 4.0;
    always #(TIN/2) clk_in = ~clk_in;

    initial begin
        $dumpfile("clk_div_odd.vcd");
        $dumpvars(0, tb_clk_div_odd);
    end

    time t_rise0, t_rise1, t_fall0;

    initial begin
        rst_n = 0;
        repeat (6) @(posedge clk_in);
        rst_n = 1;
        repeat (2) @(posedge clk_in);   // let counters reach steady phase relationship

        repeat (4) begin   // check several consecutive periods for consistency
            @(posedge clk_out);
            t_rise0 = $time;
            @(negedge clk_out);
            t_fall0 = $time;
            @(posedge clk_out);
            t_rise1 = $time;

            checks++;
            if ((t_rise1 - t_rise0) != DIV * TIN) begin
                $display("ERROR: period=%0t expected=%0t", t_rise1 - t_rise0, DIV*TIN);
                errors++;
            end else begin
                $display("period OK: %0t", t_rise1 - t_rise0);
            end

            checks++;
            // 50% duty on an ODD divisor means high time = DIV*TIN/2 (a half-integer
            // number of input periods -- e.g. 1.5, 2.5 input periods -- which is
            // exactly representable since TIN itself has a .0 that can halve evenly)
            if ((t_fall0 - t_rise0) != (DIV*TIN)/2) begin
                $display("ERROR: high_time=%0t expected=%0t", t_fall0 - t_rise0, (DIV*TIN)/2);
                errors++;
            end else begin
                $display("duty OK: high_time=%0t (%0.1f%% of period)", t_fall0-t_rise0, 100.0*(t_fall0-t_rise0)/(DIV*TIN));
            end
        end

        $display("--------------------------------------------------");
        if (errors == 0) $display("CLK_DIV_ODD (DIV=%0d): ALL %0d CHECKS PASSED -- exact 50%% duty confirmed", DIV, checks);
        else $display("CLK_DIV_ODD: %0d ERRORS out of %0d checks", errors, checks);
        $display("--------------------------------------------------");
        #50 $finish;
    end
endmodule

04_clock_dividers/clk_div_odd.vcd
$date
	Wed Jul  1 19:52:05 2026
$end
$version
	Icarus Verilog
$end
$timescale
	1ps
$end
$scope module tb_clk_div_odd $end
$var wire 1 ! clk_out $end
$var parameter 32 " DIV $end
$var real 1 # TIN $end
$var reg 1 $ clk_in $end
$var reg 1 % rst_n $end
$var reg 64 & t_fall0 [63:0] $end
$var reg 64 ' t_rise0 [63:0] $end
$var reg 64 ( t_rise1 [63:0] $end
$var integer 32 ) checks [31:0] $end
$var integer 32 * errors [31:0] $end
$scope module dut $end
$var wire 1 $ clk_in $end
$var wire 1 ! clk_out $end
$var wire 1 % rst_n $end
$var wire 1 + tmp2 $end
$var wire 1 , tmp1 $end
$var parameter 32 - CW $end
$var parameter 32 . DIV $end
$var parameter 32 / H $end
$var reg 2 0 cnt_n [1:0] $end
$var reg 2 1 cnt_p [1:0] $end
$upscope $end
$upscope $end
$enddefinitions $end
$comment Show the parameter values. $end
$dumpall
b10 /
b11 .
b10 -
r4 #
b11 "
$end
#0
$dumpvars
b0 1
b0 0
1,
1+
b0 *
b0 )
bx (
bx '
bx &
0%
0$
1!
$end
#2000
1$
#4000
0$
#6000
1$
#8000
0$
#10000
1$
#12000
0$
#14000
1$
#16000
0$
#18000
1$
#20000
0$
#22000
b1 1
1%
1$
#24000
b1 0
0$
#26000
0!
0,
b10 1
1$
#28000
0+
b10 0
0$
#30000
1,
b0 1
1$
#32000
b100000 '
1!
1+
b0 0
0$
#34000
b1 1
1$
#36000
b1 0
0$
#38000
b100110 &
0!
0,
b10 1
1$
#40000
0+
b10 0
0$
#42000
1,
b0 1
1$
#44000
b10 )
b101100 (
1!
1+
b0 0
0$
#46000
b1 1
1$
#48000
b1 0
0$
#50000
0!
0,
b10 1
1$
#52000
0+
b10 0
0$
#54000
1,
b0 1
1$
#56000
b111000 '
1!
1+
b0 0
0$
#58000
b1 1
1$
#60000
b1 0
0$
#62000
b111110 &
0!
0,
b10 1
1$
#64000
0+
b10 0
0$
#66000
1,
b0 1
1$
#68000
b100 )
b1000100 (
1!
1+
b0 0
0$
#70000
b1 1
1$
#72000
b1 0
0$
#74000
0!
0,
b10 1
1$
#76000
0+
b10 0
0$
#78000
1,
b0 1
1$
#80000
b1010000 '
1!
1+
b0 0
0$
#82000
b1 1
1$
#84000
b1 0
0$
#86000
b1010110 &
0!
0,
b10 1
1$
#88000
0+
b10 0
0$
#90000
1,
b0 1
1$
#92000
b110 )
b1011100 (
1!
1+
b0 0
0$
#94000
b1 1
1$
#96000
b1 0
0$
#98000
0!
0,
b10 1
1$
#100000
0+
b10 0
0$
#102000
1,
b0 1
1$
#104000
b1101000 '
1!
1+
b0 0
0$
#106000
b1 1
1$
#108000
b1 0
0$
#110000
b1101110 &
0!
0,
b10 1
1$
#112000
0+
b10 0
0$
#114000
1,
b0 1
1$
#116000
b1000 )
b1110100 (
1!
1+
b0 0
0$
#118000
b1 1
1$
#120000
b1 0
0$
#122000
0!
0,
b10 1
1$
#124000
0+
b10 0
0$
#126000
1,
b0 1
1$
#128000
1!
1+
b0 0
0$
#130000
b1 1
1$
#132000
b1 0
0$
#134000
0!
0,
b10 1
1$
#136000
0+
b10 0
0$
#138000
1,
b0 1
1$
#140000
1!
1+
b0 0
0$
#142000
b1 1
1$
#144000
b1 0
0$
#146000
0!
0,
b10 1
1$
#148000
0+
b10 0
0$
#150000
1,
b0 1
1$
#152000
1!
1+
b0 0
0$
#154000
b1 1
1$
#156000
b1 0
0$
#158000
0!
0,
b10 1
1$
#160000
0+
b10 0
0$
#162000
1,
b0 1
1$
#164000
1!
1+
b0 0
0$
#166000
b1 1
1$
