02_async_fifo/async_fifo.sv
// =============================================================================
// async_fifo.sv - Dual-Clock (Asynchronous) FIFO
// -----------------------------------------------------------------------------
// The classic Clifford E. Cummings structure. Two separate clock domains
// (write side, read side) exchange pointers safely by:
//   1. Converting binary pointers to GRAY CODE before crossing domains
//      (gray code changes only ONE bit at a time, so a synchronizer can
//       never latch a "half-updated" value that is wildly wrong -- at worst
//       it's off by one, which full/empty logic is built to tolerate).
//   2. Passing the gray pointer through a 2-flip-flop synchronizer in the
//      OTHER clock domain before it's used for full/empty comparison.
//
// FULL  is a REGISTERED flag in the WRITE clock domain, computed by comparing
//       the next write pointer to the synchronized read pointer.
// EMPTY is a REGISTERED flag in the READ clock domain, computed by comparing
//       the next read pointer to the synchronized write pointer.
// (Both are registered rather than purely combinational to avoid a subtle
//  zero-delay combinational-loop bug -- see the comment near 'full' below.)
// =============================================================================
module async_fifo #(
    parameter int WIDTH = 8,
    parameter int DEPTH = 16                  // must be a power of 2
) (
    // ---------------- write domain ----------------
    input  logic             wr_clk,
    input  logic             wr_rst_n,
    input  logic             wr_en,
    input  logic [WIDTH-1:0] wdata,
    output logic             full,

    // ---------------- read domain ----------------
    input  logic             rd_clk,
    input  logic             rd_rst_n,
    input  logic             rd_en,
    output logic [WIDTH-1:0] rdata,
    output logic             empty
);

    localparam int AW = $clog2(DEPTH);

    logic [WIDTH-1:0] mem [0:DEPTH-1];

    logic [AW:0] wbin, wbin_next, wgray, wgray_next;
    logic [AW:0] rbin, rbin_next, rgray, rgray_next;

    logic [AW:0] wq1_rgray, wq2_rgray;   // read-pointer gray, synced INTO write domain
    logic [AW:0] rq1_wgray, rq2_wgray;   // write-pointer gray, synced INTO read domain

    // =====================================================================
    // WRITE DOMAIN
    // =====================================================================
    // 2-flop synchronizer bringing the read pointer (gray) into wr_clk domain
    always_ff @(posedge wr_clk or negedge wr_rst_n) begin
        if (!wr_rst_n) {wq2_rgray, wq1_rgray} <= '0;
        else           {wq2_rgray, wq1_rgray} <= {wq1_rgray, rgray};
    end

    assign wbin_next  = wbin + (wr_en & ~full);
    assign wgray_next = (wbin_next >> 1) ^ wbin_next;      // binary -> gray

    // NOTE ON A CLASSIC PITFALL: it's tempting to write
    //   assign full = (wgray_next == {~wq2_rgray[AW:AW-1], wq2_rgray[AW-2:0]});
    // as a plain continuous assignment. DON'T -- wgray_next depends on
    // wbin_next, which itself depends on full (via "wr_en & ~full"). That
    // makes full a combinational function of itself the instant the FIFO
    // fills up, which is a genuine zero-delay oscillation (full toggles
    // 0/1/0/1... forever within the same time step and hangs the
    // simulator). The fix: register 'full' in the same always_ff as the
    // pointers, so the value used on the right-hand side of wbin_next is
    // always last cycle's stable, already-settled value.
    always_ff @(posedge wr_clk or negedge wr_rst_n) begin
        if (!wr_rst_n) begin
            wbin  <= '0;
            wgray <= '0;
            full  <= 1'b0;
        end else begin
            wbin  <= wbin_next;
            wgray <= wgray_next;
            full  <= (wgray_next == {~wq2_rgray[AW:AW-1], wq2_rgray[AW-2:0]});
        end
    end

    always_ff @(posedge wr_clk) begin
        if (wr_en && !full) mem[wbin[AW-1:0]] <= wdata;
    end

    // =====================================================================
    // READ DOMAIN
    // =====================================================================
    // 2-flop synchronizer bringing the write pointer (gray) into rd_clk domain
    always_ff @(posedge rd_clk or negedge rd_rst_n) begin
        if (!rd_rst_n) {rq2_wgray, rq1_wgray} <= '0;
        else           {rq2_wgray, rq1_wgray} <= {rq1_wgray, wgray};
    end

    assign rbin_next  = rbin + (rd_en & ~empty);
    assign rgray_next = (rbin_next >> 1) ^ rbin_next;

    always_ff @(posedge rd_clk or negedge rd_rst_n) begin
        if (!rd_rst_n) begin
            rbin  <= '0;
            rgray <= '0;
            empty <= 1'b1;
        end else begin
            rbin  <= rbin_next;
            rgray <= rgray_next;
            empty <= (rgray_next == rq2_wgray);
        end
    end

    assign rdata = mem[rbin[AW-1:0]];

endmodule

02_async_fifo/tb_async_fifo.sv
// =============================================================================
// tb_async_fifo.sv - Self-checking testbench for async_fifo
// Uses two independent, unrelated clock frequencies to genuinely exercise CDC.
// =============================================================================
`timescale 1ns/1ps
module tb_async_fifo;

    localparam int WIDTH = 8;
    localparam int DEPTH = 16;

    logic wr_clk = 0, rd_clk = 0;
    logic wr_rst_n, rd_rst_n;
    logic wr_en, rd_en;
    logic [WIDTH-1:0] wdata, rdata;
    logic full, empty;

    int errors = 0;
    int checks = 0;
    logic [WIDTH-1:0] ref_model [$];

    async_fifo #(.WIDTH(WIDTH), .DEPTH(DEPTH)) dut (
        .wr_clk(wr_clk), .wr_rst_n(wr_rst_n), .wr_en(wr_en), .wdata(wdata), .full(full),
        .rd_clk(rd_clk), .rd_rst_n(rd_rst_n), .rd_en(rd_en), .rdata(rdata), .empty(empty)
    );

    // Deliberately unrelated, non-integer-ratio clock periods to genuinely exercise CDC
    always #3.5 wr_clk = ~wr_clk;
    always #5.5 rd_clk = ~rd_clk;

    initial begin
        $dumpfile("async_fifo.vcd");
        $dumpvars(0, tb_async_fifo);
    end

    // Safety net in case of an unexpected deadlock/oscillation
    initial begin
        #500000;
        $display("WATCHDOG TIMEOUT at T=%0t -- simulation did not complete in time", $time);
        $finish;
    end

    // ---------------- Write side: drive + push into reference model ----------------
    // Checked the same way the DUT itself gates a write: using the pre-edge
    // (already-settled) value of 'full', sampled right at the posedge.
    always @(posedge wr_clk) begin
        if (wr_rst_n && wr_en && !full) begin
            ref_model.push_back(wdata);
        end
    end

    initial begin
        wr_en = 0; wdata = 0; wr_rst_n = 0;
        repeat (4) @(posedge wr_clk);
        wr_rst_n = 1;

        for (int i = 0; i < 400; i++) begin
            @(negedge wr_clk);
            wr_en = ($urandom_range(0,9) < 7);   // ~70% write attempt rate
            wdata = i[WIDTH-1:0];
        end
        @(negedge wr_clk);
        wr_en = 0;
    end

    // ---------------- Read side: checker samples at posedge (matches NBA/register semantics) ----------------
    always @(posedge rd_clk) begin
        if (rd_rst_n && rd_en && !empty) begin
            checks++;
            if (ref_model.size() == 0) begin
                $display("[%0t] ERROR: read claimed valid data but ref model is empty!", $time);
                errors++;
            end else begin
                logic [WIDTH-1:0] exp;
                exp = ref_model.pop_front();
                if (rdata !== exp) begin
                    $display("[%0t] ERROR: rdata=%0h expected=%0h", $time, rdata, exp);
                    errors++;
                end
            end
        end
    end

    // ---------------- Read side driver ----------------
    initial begin
        rd_en = 0; rd_rst_n = 0;
        repeat (4) @(posedge rd_clk);
        rd_rst_n = 1;

        // Give the write side a head start so the FIFO has data to drain
        repeat (20) @(posedge rd_clk);

        for (int i = 0; i < 600; i++) begin
            @(negedge rd_clk);
            rd_en = ($urandom_range(0,9) < 6);   // ~60% read attempt rate
        end
        @(negedge rd_clk);
        rd_en = 0;

        // Drain whatever remains
        for (int i = 0; i < 300; i++) begin
            @(negedge rd_clk);
            rd_en = !empty;
        end
        @(negedge rd_clk);
        rd_en = 0;

        repeat (5) @(posedge rd_clk);

        $display("--------------------------------------------------");
        if (errors == 0 && ref_model.size() == 0)
            $display("ASYNC FIFO: ALL %0d CHECKS PASSED (reference model fully drained)", checks);
        else
            $display("ASYNC FIFO: %0d ERRORS out of %0d checks, %0d items left un-drained",
                      errors, checks, ref_model.size());
        $display("--------------------------------------------------");
        #100 $finish;
    end

endmodule

02_async_fifo/async_fifo.vcd
$date
	Wed Jul  1 19:38:01 2026
$end
$version
	Icarus Verilog
$end
$timescale
	1ps
$end
$scope module tb_async_fifo $end
$var wire 8 ! rdata [7:0] $end
$var wire 1 " full $end
$var wire 1 # empty $end
$var parameter 32 $ DEPTH $end
$var parameter 32 % WIDTH $end
$var reg 1 & rd_clk $end
$var reg 1 ' rd_en $end
$var reg 1 ( rd_rst_n $end
$var reg 8 ) wdata [7:0] $end
$var reg 1 * wr_clk $end
$var reg 1 + wr_en $end
$var reg 1 , wr_rst_n $end
$var integer 32 - checks [31:0] $end
$var integer 32 . errors [31:0] $end
$scope module dut $end
$var wire 1 & rd_clk $end
$var wire 1 ' rd_en $end
$var wire 1 ( rd_rst_n $end
$var wire 8 / rdata [7:0] $end
$var wire 5 0 rgray_next [4:0] $end
$var wire 8 1 wdata [7:0] $end
$var wire 5 2 wgray_next [4:0] $end
$var wire 1 * wr_clk $end
$var wire 1 + wr_en $end
$var wire 1 , wr_rst_n $end
$var wire 5 3 wbin_next [4:0] $end
$var wire 5 4 rbin_next [4:0] $end
$var parameter 32 5 AW $end
$var parameter 32 6 DEPTH $end
$var parameter 32 7 WIDTH $end
$var reg 1 # empty $end
$var reg 1 " full $end
$var reg 5 8 rbin [4:0] $end
$var reg 5 9 rgray [4:0] $end
$var reg 5 : rq1_wgray [4:0] $end
$var reg 5 ; rq2_wgray [4:0] $end
$var reg 5 < wbin [4:0] $end
$var reg 5 = wgray [4:0] $end
$var reg 5 > wq1_rgray [4:0] $end
$var reg 5 ? wq2_rgray [4:0] $end
$upscope $end
$scope begin $ivl_for_loop0 $end
$var integer 32 @ i [31:0] $end
$upscope $end
$scope begin $ivl_for_loop1 $end
$var integer 32 A i [31:0] $end
$upscope $end
$scope begin $ivl_for_loop2 $end
$var integer 32 B i [31:0] $end
$upscope $end
$scope begin $unm_blk_19 $end
$var reg 8 C exp [7:0] $end
$upscope $end
$upscope $end
$enddefinitions $end
$comment Show the parameter values. $end
$dumpall
b1000 7
b10000 6
b100 5
b1000 %
b10000 $
$end
#0
$dumpvars
bx C
b0 B
b0 A
b0 @
b0 ?
b0 >
b0 =
b0 <
b0 ;
b0 :
b0 9
b0 8
b0 4
b0 3
b0 2
b0 1
b0 0
bx /
b0 .
b0 -
0,
0+
0*
b0 )
0(
0'
0&
1#
0"
bx !
$end
#3500
1*
#5500
1&
#7000
0*
#10500
1*
#11000
0&
#14000
0*
#16500
1&
#17500
1*
#21000
0*
#22000
0&
#24500
1,
1*
#27500
1&
#28000
b1 2
b1 3
b1 @
1+
0*
#31500
b11 2
b0 !
b0 /
b1 =
b10 3
b1 <
1*
#33000
0&
#35000
b10 @
b1 )
b1 1
0*
#38500
b10 2
b11 =
b11 3
b10 <
b1 :
1(
1*
1&
#42000
b11 @
b10 )
b10 1
0*
#44000
0&
#45500
b110 2
b10 =
b100 3
b11 <
1*
#49000
b100 @
b11 )
b11 1
0*
#49500
b1 ;
b10 :
1&
#52500
b111 2
b110 =
b101 3
b100 <
1*
#55000
0&
#56000
b101 @
b100 )
b100 1
0*
#59500
b101 2
b111 =
b110 3
b101 <
1*
#60500
b10 ;
b111 :
0#
1&
#63000
b111 2
b101 3
b110 @
b101 )
b101 1
0+
0*
#66000
0&
#66500
1*
#70000
b101 2
b110 3
b111 @
b110 )
b110 1
1+
0*
#71500
b111 ;
1&
#73500
b100 2
b101 =
b111 3
b110 <
1*
#77000
b1000 @
b111 )
b111 1
0*
0&
#80500
b1100 2
b100 =
b1000 3
b111 <
1*
#82500
b100 :
1&
#84000
b1001 @
b1000 )
b1000 1
0*
#87500
b1101 2
b1100 =
b1001 3
b1000 <
1*
#88000
0&
#91000
b1010 @
b1001 )
b1001 1
0*
#93500
b100 ;
b1100 :
1&
#94500
b1111 2
b1101 =
b1010 3
b1001 <
1*
#98000
b1101 2
b1001 3
b1011 @
b1010 )
b1010 1
0+
0*
#99000
0&
#101500
1*
#104500
b1100 ;
b1101 :
1&
#105000
b1111 2
b1010 3
b1100 @
b1011 )
b1011 1
1+
0*
#108500
b1110 2
b1111 =
b1011 3
b1010 <
1*
#110000
0&
#112000
b1111 2
b1010 3
b1101 @
b1100 )
b1100 1
0+
0*
#115500
b1101 ;
b1111 :
1*
1&
#119000
b1110 @
b1101 )
b1101 1
0*
#121000
0&
#122500
1*
#126000
b1111 @
b1110 )
b1110 1
0*
#126500
b1111 ;
1&
#129500
1*
#132000
0&
#133000
b1110 2
b1011 3
b10000 @
b1111 )
b1111 1
1+
0*
#136500
b1010 2
b1110 =
b1100 3
b1011 <
1*
#137500
b1110 :
1&
#140000
b10001 @
b10000 )
b10000 1
0*
#143000
0&
#143500
b1011 2
b1010 =
b1101 3
b1100 <
1*
#147000
b10010 @
b10001 )
b10001 1
0*
#148500
b1110 ;
b1010 :
1&
#150500
b1001 2
b1011 =
b1110 3
b1101 <
1*
#154000
b1011 2
b1101 3
b10011 @
b10010 )
b10010 1
0+
0*
0&
#157500
1*
#159500
b1010 ;
b1011 :
1&
#161000
b1001 2
b1110 3
b10100 @
b10011 )
b10011 1
1+
0*
#164500
b1000 2
b1001 =
b1111 3
b1110 <
1*
#165000
0&
#168000
b10101 @
b10100 )
b10100 1
0*
#170500
b1011 ;
b1001 :
1&
#171500
b11000 2
b1000 =
b10000 3
b1111 <
1*
#175000
b1000 2
b1111 3
b10110 @
b10101 )
b10101 1
0+
0*
#176000
0&
#178500
1*
#181500
b1001 ;
b1000 :
1&
#182000
b10111 @
b10110 )
b10110 1
0*
#185500
1*
#187000
0&
#189000
b11000 2
b10000 3
b11000 @
b10111 )
b10111 1
1+
0*
#192500
b11000 2
1"
b11000 =
b10000 3
b10000 <
b1000 ;
1*
1&
#196000
b11001 @
b11000 )
b11000 1
0*
#198000
0&
#199500
1*
#203000
b11010 @
b11001 )
b11001 1
0*
#203500
b11000 :
1&
#206500
1*
#209000
0&
#210000
b11011 @
b11010 )
b11010 1
0*
#213500
1*
#214500
b11000 ;
1&
#217000
b11100 @
b11011 )
b11011 1
0*
#220000
0&
#220500
1*
#224000
b11101 @
b11100 )
b11100 1
0*
#225500
1&
#227500
1*
#231000
b11110 @
b11101 )
b11101 1
0*
0&
#234500
1*
#236500
1&
#238000
b11111 @
b11110 )
b11110 1
0*
#241500
1*
#242000
0&
#245000
b100000 @
b11111 )
b11111 1
0*
#247500
1&
#248500
1*
#252000
b100001 @
b100000 )
b100000 1
0*
#253000
0&
#255500
1*
#258500
1&
#259000
b100010 @
b100001 )
b100001 1
0*
#262500
1*
#264000
b1 A
0&
#266000
b100011 @
b100010 )
b100010 1
0*
#269500
1*
1&
#273000
b100100 @
b100011 )
b100011 1
0*
#275000
b1 0
b1 4
b10 A
1'
0&
#276500
1*
#280000
b100101 @
b100100 )
b100100 1
0*
#280500
b11 0
b1 !
b1 /
b1 9
b10 4
b1 8
b0 C
b1 -
1&
#283500
b1 >
1*
#286000
b11 A
0&
#287000
b100110 @
b100101 )
b100101 1
0+
0*
#290500
b1 ?
1*
#291500
b10 0
b10 !
b10 /
b11 9
b11 4
b10 8
b1 C
b10 -
1&
#294000
b100111 @
b100110 )
b100110 1
1+
0*
#297000
b100 A
0&
#297500
b11001 2
b10001 3
0"
b11 >
1*
#301000
b101000 @
b100111 )
b100111 1
0*
#302500
b110 0
b11 !
b11 /
b10 9
b100 4
b11 8
b10 C
b11 -
1&
#304500
b11001 2
b11 ?
b10 >
1"
b11001 =
b10001 3
b10001 <
1*
#308000
b101001 @
b101000 )
b101000 1
b101 A
0*
0&
#311500
b11011 2
b10010 3
0"
b10 ?
1*
#313500
b111 0
b100 !
b100 /
b110 9
b101 4
b100 8
b11001 :
b11 C
b100 -
1&
#315000
b101010 @
b101001 )
b101001 1
0*
#318500
b11010 2
b110 >
b11011 =
b10011 3
b10010 <
1*
#319000
b110 A
0&
#322000
b101011 @
b101010 )
b101010 1
0*
#324500
b101 0
b110 !
b110 /
b11001 ;
b11011 :
b111 9
b110 4
b101 8
b100 C
b101 -
1&
#325500
b11010 2
1"
b11010 =
b10011 3
b10011 <
b110 ?
b111 >
1*
#329000
b101100 @
b101011 )
b101011 1
0*
#330000
b111 0
b101 4
b111 A
0'
0&
#332500
b11110 2
b10100 3
b111 ?
0"
1*
#335500
b11011 ;
b11010 :
1&
#336000
b11010 2
b10011 3
b101101 @
b101100 )
b101100 1
0+
0*
#339500
1*
#341000
b1000 A
0&
#343000
b11110 2
b10100 3
b101110 @
b101101 )
b101101 1
1+
0*
#346500
b11111 2
b11110 =
b10101 3
b10100 <
b11010 ;
1*
1&
#350000
b11110 2
b10100 3
b101111 @
b101110 )
b101110 1
0+
0*
#352000
b101 0
b110 4
b1001 A
1'
0&
#353500
1*
#357000
b110000 @
b101111 )
b101111 1
0*
#357500
b100 0
b111 !
b111 /
b101 9
b111 4
b110 8
b11110 :
b110 C
b110 -
1&
#360500
b101 >
1*
#363000
b101 0
b110 4
b1010 A
0'
0&
#364000
b110001 @
b110000 )
b110000 1
0*
#367500
b101 ?
1*
#368500
b11110 ;
1&
#371000
b110010 @
b110001 )
b110001 1
0*
#374000
b100 0
b111 4
b1011 A
1'
0&
#374500
1*
#378000
b11111 2
b10101 3
b110011 @
b110010 )
b110010 1
1+
0*
#379500
b1100 0
b1000 !
b1000 /
b100 9
b1000 4
b111 8
b111 C
b111 -
1&
#381500
b11101 2
b11111 =
b10110 3
b10101 <
b100 >
1*
#385000
b110100 @
b110011 )
b110011 1
b1100 A
0*
0&
#388500
b11101 2
b100 ?
1"
b11101 =
b10110 3
b10110 <
1*
#390500
b1101 0
b1001 !
b1001 /
b11101 :
b1100 9
b1001 4
b1000 8
b1000 C
b1000 -
1&
#392000
b110101 @
b110100 )
b110100 1
0+
0*
#395500
0"
b1100 >
1*
#396000
b1100 0
b1000 4
b1101 A
0'
0&
#399000
b11100 2
b10111 3
b110110 @
b110101 )
b110101 1
1+
0*
#401500
b11101 ;
1&
#402500
b11100 2
b1100 ?
1"
b11100 =
b10111 3
b10111 <
1*
#406000
b110111 @
b110110 )
b110110 1
0*
#407000
b1101 0
b1001 4
b1110 A
1'
0&
#409500
b10100 2
b11000 3
0"
1*
#412500
b1111 0
b1011 !
b1011 /
b11100 :
b1101 9
b1010 4
b1001 8
b1001 C
b1001 -
1&
#413000
b111000 @
b110111 )
b110111 1
0*
#416500
b10100 2
b1101 >
1"
b10100 =
b11000 3
b11000 <
1*
#418000
b1101 0
b1001 4
b1111 A
0'
0&
#420000
b111001 @
b111000 )
b111000 1
0+
0*
#423500
b1101 ?
b11100 ;
b10100 :
1*
1&
#427000
b111010 @
b111001 )
b111001 1
1+
0*
#429000
b10000 A
0&
#430500
b10101 2
b11001 3
0"
1*
#434000
b10100 2
b11000 3
b111011 @
b111010 )
b111010 1
0+
0*
#434500
b10100 ;
1&
#437500
1*
#440000
b10001 A
0&
#441000
b111100 @
b111011 )
b111011 1
0*
#444500
1*
#445500
1&
#448000
b10101 2
b11001 3
b111101 @
b111100 )
b111100 1
1+
0*
#451000
b1111 0
b1010 4
b10010 A
1'
0&
#451500
b10101 2
1"
b10101 =
b11001 3
b11001 <
1*
#455000
b111110 @
b111101 )
b111101 1
0*
#456500
b1110 0
b1111 !
b1111 /
b10101 :
b1111 9
b1011 4
b1010 8
b1011 C
b1010 -
1&
#458500
b1111 >
1*
#462000
b111111 @
b111110 )
b111110 1
0+
b10011 A
0*
0&
#465500
b1111 ?
1*
#467500
b1010 0
b10000 !
b10000 /
b1110 9
b1100 4
b1011 8
b10101 ;
b1111 C
b1011 -
1&
#469000
b1000000 @
b111111 )
b111111 1
1+
0*
#472500
b10111 2
b11010 3
b1110 >
0"
1*
#473000
b10100 A
0&
#476000
b1000001 @
b1000000 )
b1000000 1
0*
#478500
b1011 0
b10001 !
b10001 /
b1010 9
b1101 4
b1100 8
b10000 C
b1100 -
1&
#479500
b10111 2
1"
b10111 =
b11010 3
b11010 <
b1110 ?
b1010 >
1*
#483000
b1000010 @
b1000001 )
b1000001 1
0*
#484000
b1010 0
b1100 4
b10101 A
0'
0&
#486500
b10110 2
b11011 3
b1010 ?
0"
1*
#489500
b10111 :
1&
#490000
b1000011 @
b1000010 )
b1000010 1
0*
#493500
b10010 2
b10110 =
b11100 3
b11011 <
1*
#495000
b1011 0
b1101 4
b10110 A
1'
0&
#497000
b10110 2
b11011 3
b1000100 @
b1000011 )
b1000011 1
0+
0*
#500500
b1001 0
b10011 !
b10011 /
b10111 ;
b10110 :
b1011 9
b1110 4
b1101 8
b10001 C
b1101 -
1*
1&
#504000
b10010 2
b11100 3
b1000101 @
b1000100 )
b1000100 1
1+
0*
#506000
b1011 0
b1101 4
b10111 A
0'
0&
#507500
b10010 2
1"
b10010 =
b11100 3
b11100 <
b1011 >
1*
#511000
b1000110 @
b1000101 )
b1000101 1
0*
#511500
b10110 ;
b10010 :
1&
#514500
b1011 ?
1*
#517000
b1001 0
b1110 4
b11000 A
1'
0&
#518000
b1000111 @
b1000110 )
b1000110 1
0+
0*
#521500
0"
1*
#522500
b1000 0
b10100 !
b10100 /
b10010 ;
b1001 9
b1111 4
b1110 8
b10011 C
b1110 -
1&
#525000
b10011 2
b11101 3
b1001000 @
b1000111 )
b1000111 1
1+
0*
#528000
b11001 A
0&
#528500
b10011 2
b1001 >
1"
b10011 =
b11101 3
b11101 <
1*
#532000
b1001001 @
b1001000 )
b1001000 1
0*
#533500
b11000 0
b10111 !
b10111 /
b1000 9
b10000 4
b1111 8
b10011 :
b10100 C
b1111 -
1&
#535500
b1001 ?
b1000 >
1*
#539000
b1000 0
b1111 4
b1001010 @
b1001001 )
b1001001 1
b11010 A
0'
0*
0&
#542500
b10001 2
b11110 3
b1000 ?
0"
1*
#544500
b10011 ;
1&
#546000
b1001011 @
b1001010 )
b1001010 1
0*
#549500
b10000 2
b10001 =
b11111 3
b11110 <
1*
#550000
b11011 A
0&
#553000
b1001100 @
b1001011 )
b1001011 1
0*
#555500
b10001 :
1&
#556500
b10000 2
1"
b10000 =
b11111 3
b11111 <
1*
#560000
b1001101 @
b1001100 )
b1001100 1
0*
#561000
b11100 A
0&
#563500
1*
#566500
b10001 ;
b10000 :
1&
#567000
b1001110 @
b1001101 )
b1001101 1
0*
#570500
1*
#572000
b11000 0
b10000 4
b11101 A
1'
0&
#574000
b1001111 @
b1001110 )
b1001110 1
0*
#577500
b11001 0
b100111 !
b100111 /
b11000 9
b10001 4
b10000 8
b10000 ;
b10111 C
b10000 -
1*
1&
#581000
b1010000 @
b1001111 )
b1001111 1
0+
0*
#583000
b11110 A
0&
#584500
b11000 >
1*
#588000
b1010001 @
b1010000 )
b1010000 1
0*
#588500
b11011 0
b101001 !
b101001 /
b11001 9
b10010 4
b10001 8
b100111 C
b10001 -
1&
#591500
b11000 ?
b11001 >
1*
#594000
b11111 A
0&
#595000
b1010010 @
b1010001 )
b1010001 1
1+
0*
#598500
b0 2
b0 3
b11001 ?
0"
1*
#599500
b11010 0
b101010 !
b101010 /
b11011 9
b10011 4
b10010 8
b101001 C
b10010 -
1&
#602000
b1010011 @
b1010010 )
b1010010 1
0*
#605000
b100000 A
0&
#605500
b1 2
b0 =
b1 3
b0 <
b11011 >
1*
#609000
b1010100 @
b1010011 )
b1010011 1
0*
#610500
b11110 0
b101101 !
b101101 /
b0 :
b11010 9
b10100 4
b10011 8
b101010 C
b10011 -
1&
#612500
b1 2
b11011 ?
b11010 >
1"
b1 =
b1 3
b1 <
1*
#616000
b11010 0
b10011 4
b1010101 @
b1010100 )
b1010100 1
b100001 A
0'
0*
0&
#619500
b11 2
b10 3
0"
b11010 ?
1*
#621500
b0 ;
b1 :
1&
#623000
b1010110 @
b1010101 )
b1010101 1
0*
#626500
b10 2
b11 =
b11 3
b10 <
1*
#627000
b100010 A
0&
#630000
b1010111 @
b1010110 )
b1010110 1
0*
#632500
b1 ;
b11 :
1&
#633500
b10 2
1"
b10 =
b11 3
b11 <
1*
#637000
b1011000 @
b1010111 )
b1010111 1
0*
#638000
b11110 0
b10100 4
b100011 A
1'
0&
#640500
1*
#643500
b11111 0
b110010 !
b110010 /
b11110 9
b10101 4
b10100 8
b11 ;
b10 :
b101101 C
b10100 -
1&
#644000
b1011001 @
b1011000 )
b1011000 1
0*
#647500
b11110 >
1*
#649000
b100100 A
0&
#651000
b1011010 @
b1011001 )
b1011001 1
0*
#654500
b11101 0
b110011 !
b110011 /
b11110 ?
b10 ;
b11111 9
b10110 4
b10101 8
b110010 C
b10101 -
1*
1&
#658000
b1011011 @
b1011010 )
b1011010 1
0+
0*
#660000
b11111 0
b10101 4
b100101 A
0'
0&
#661500
0"
b11111 >
1*
#665000
b110 2
b100 3
b1011100 @
b1011011 )
b1011011 1
1+
0*
#665500
1&
#668500
b110 2
b11111 ?
1"
b110 =
b100 3
b100 <
1*
#671000
b11101 0
b10110 4
b100110 A
1'
0&
#672000
b1011101 @
b1011100 )
b1011100 1
0+
0*
#675500
0"
1*
#676500
b11100 0
b110101 !
b110101 /
b110 :
b11101 9
b10111 4
b10110 8
b110011 C
b10110 -
1&
#679000
b111 2
b101 3
b1011110 @
b1011101 )
b1011101 1
1+
0*
#682000
b11101 0
b10110 4
b100111 A
0'
0&
#682500
b111 2
b11101 >
1"
b111 =
b101 3
b101 <
1*
#686000
b1011111 @
b1011110 )
b1011110 1
0*
#687500
b110 ;
b111 :
1&
#689500
b11101 ?
1*
#693000
b11100 0
b10111 4
b1100000 @
b1011111 )
b1011111 1
b101000 A
1'
0*
0&
#696500
b101 2
b110 3
0"
1*
#698500
b10100 0
b110111 !
b110111 /
b111 ;
b11100 9
b11000 4
b10111 8
b110101 C
b10111 -
1&
#700000
b1100001 @
b1100000 )
b1100000 1
0*
#703500
b101 2
1"
b101 =
b110 3
b110 <
b11100 >
1*
#704000
b11100 0
b10111 4
b101001 A
0'
0&
#707000
b1100010 @
b1100001 )
b1100001 1
0*
#709500
b101 :
1&
#710500
b11100 ?
1*
#714000
b1100011 @
b1100010 )
b1100010 1
0*
#715000
b101010 A
0&
#717500
b100 2
b111 3
0"
1*
#720500
b101 ;
1&
#721000
b1100100 @
b1100011 )
b1100011 1
0*
#724500
b100 2
1"
b100 =
b111 3
b111 <
1*
#726000
b101011 A
0&
#728000
b1100101 @
b1100100 )
b1100100 1
0*
#731500
b100 :
1*
1&
#735000
b1100110 @
b1100101 )
b1100101 1
0+
0*
#737000
b101100 A
0&
#738500
1*
#742000
b1100111 @
b1100110 )
b1100110 1
1+
0*
#742500
b100 ;
1&
#745500
1*
#748000
b10100 0
b11000 4
b101101 A
1'
0&
#749000
b1101000 @
b1100111 )
b1100111 1
0+
0*
#752500
1*
#753500
b10101 0
b111100 !
b111100 /
b10100 9
b11001 4
b11000 8
b110111 C
b11000 -
1&
#756000
b1101001 @
b1101000 )
b1101000 1
1+
0*
#759000
b10100 0
b11000 4
b101110 A
0'
0&
#759500
b10100 >
1*
#763000
b1101010 @
b1101001 )
b1101001 1
0*
#764500
1&
#766500
b10100 ?
1*
#770000
b10101 0
b11001 4
b1101011 @
b1101010 )
b1101010 1
0+
b101111 A
1'
0*
0&
#773500
0"
1*
#775500
b10111 0
b1000000 !
b1000000 /
b10101 9
b11010 4
b11001 8
b111100 C
b11001 -
1&
#777000
b1101100 @
b1101011 )
b1101011 1
0*
#780500
b10101 >
1*
#781000
b10101 0
b11001 4
b110000 A
0'
0&
#784000
b1100 2
b1000 3
b1101101 @
b1101100 )
b1101100 1
1+
0*
#786500
1&
#787500
b1100 2
1"
b1100 =
b1000 3
b1000 <
b10101 ?
1*
#791000
b1101110 @
b1101101 )
b1101101 1
0*
#792000
b110001 A
0&
#794500
b1101 2
b1001 3
0"
1*
#797500
b1100 :
1&
#798000
b1100 2
b1000 3
b1101111 @
b1101110 )
b1101110 1
0+
0*
#801500
1*
#803000
b10111 0
b11010 4
b110010 A
1'
0&
#805000
b1110000 @
b1101111 )
b1101111 1
0*
#808500
b10110 0
b1000010 !
b1000010 /
b1100 ;
b10111 9
b11011 4
b11010 8
b1000000 C
b11010 -
1*
1&
#812000
b1101 2
b1001 3
b1110001 @
b1110000 )
b1110000 1
1+
0*
#814000
b110011 A
0&
#815500
b1101 2
1"
b1101 =
b1001 3
b1001 <
b10111 >
1*
#819000
b1110010 @
b1110001 )
b1110001 1
0*
#819500
b10010 0
b1000100 !
b1000100 /
b10110 9
b11100 4
b11011 8
b1101 :
b1000010 C
b11011 -
1&
#822500
b10111 ?
b10110 >
1*
#825000
b110100 A
0&
#826000
b1110011 @
b1110010 )
b1110010 1
0*
#829500
b1111 2
b1010 3
0"
b10110 ?
1*
#830500
b10011 0
b1000111 !
b1000111 /
b1101 ;
b10010 9
b11101 4
b11100 8
b1000100 C
b11100 -
1&
#833000
b1110100 @
b1110011 )
b1110011 1
0*
#836000
b110101 A
0&
#836500
b1110 2
b10010 >
b1111 =
b1011 3
b1010 <
1*
#840000
b1110101 @
b1110100 )
b1110100 1
0*
#841500
b10001 0
b1001010 !
b1001010 /
b10011 9
b11110 4
b11101 8
b1111 :
b1000111 C
b11101 -
1&
#843500
b1110 2
1"
b1110 =
b1011 3
b1011 <
b10010 ?
b10011 >
1*
#847000
b1110110 @
b1110101 )
b1110101 1
0+
b110110 A
0*
0&
#850500
b10011 ?
0"
1*
#852500
b10000 0
b1001011 !
b1001011 /
b1111 ;
b1110 :
b10001 9
b11111 4
b11110 8
b1001010 C
b11110 -
1&
#854000
b1010 2
b1100 3
b1110111 @
b1110110 )
b1110110 1
1+
0*
#857500
b1011 2
b1010 =
b1101 3
b1100 <
b10001 >
1*
#858000
b110111 A
0&
#861000
b1010 2
b1100 3
b1111000 @
b1110111 )
b1110111 1
0+
0*
#863500
b0 0
b1010010 !
b1010010 /
b10000 9
b0 4
b11111 8
b1110 ;
b1010 :
b1001011 C
b11111 -
1&
#864500
b10001 ?
b10000 >
1*
#868000
b1011 2
b1101 3
b1111001 @
b1111000 )
b1111000 1
1+
0*
#869000
b111000 A
0&
#871500
b1001 2
b1011 =
b1110 3
b1101 <
b10000 ?
1*
#874500
b1 0
b1010011 !
b1010011 /
b1010 ;
b1011 :
b0 9
b1 4
b0 8
b1010010 C
b100000 -
1&
#875000
b1011 2
b1101 3
b1111010 @
b1111001 )
b1111001 1
0+
0*
#878500
b0 >
1*
#880000
b0 0
b0 4
b111001 A
0'
0&
#882000
b1111011 @
b1111010 )
b1111010 1
0*
